Workbook

Sheet afastamentos-do-pais-dos-2023
A1: Perspectiva | B1: ID | C1: Dimensão | D1: Peso | E1: Nível (0-5) | F1: Itens Observados | G1: Total
A2: Dados Abertos | B2: D1 | C2: Dados completos | D2: 1 | E2: 0 | F2: Com base na análise do conjunto de dados "Afastamentos do País dos Servidores do IFMG 2023", observa-se que este não consta no PDA da instituição. A ausência do referido conjunto representa uma lacuna de evidência, uma vez que este instrumento formaliza o escopo e os critérios de completude esperados para cada conjunto de dados, como a abrangência da série histórica e a totalidade das variáveis a serem publicadas. Sem essa definição prévia, a avaliação objetiva da completude, conforme preconizado pela dimensão D1, torna-se inviável. Diante da inexistência de uma definição formal para o item avaliado no âmbito do PDA, atribui-se o Nível 0 a esta dimensão. A justificativa técnica alinha-se à definição da métrica DGABr, que classifica como Nível 0 as situações em que não há um padrão estabelecido pela instituição para o critério em análise. A impossibilidade de verificar se os dados publicados correspondem integralmente ao planejado impede a atribuição de níveis superiores, que pressupõem um percentual de cumprimento aferível. | G2: =E2*D2 -> 0
A3: Dados Abertos | B3: D2 | C3: Dados primários | D3: 1 | E3: 5 | F3: A análise do conjunto de dados indica que a fonte primária da informação são as portarias originadas no SEI e publicadas na Imprensa Nacional. O conjunto de dados preserva as informações originais, transcrevendo os campos relevantes dos documentos-fonte sem aplicar agregações ou modificações que alterem a granularidade dos registros. A manutenção integral da natureza bruta da informação, coletada diretamente da fonte, caracteriza o dado como primário, conforme a definição da dimensão D2 da métrica. Visto que 100% dos registros atendem ao critério de dado primário, o Nível 5 é atribuído, em conformidade com a escala de avaliação da métrica. Registra-se que o conjunto de dados não consta no PDA, uma observação pertinente a outras dimensões da avaliação, mas que não interfere na análise da granularidade dos dados para a presente dimensão. | G3: =E3*D3 -> 5
A4: Dados Abertos | B4: D3 | C4: Dados atualizados / DGA atualizado | D4: 1 | E4: 0 | F4: A análise do PDA indica que o conjunto de dados em avaliação não se encontra nele inventariado. Consequentemente, não há uma frequência de atualização formalmente definida para o referido conjunto, o que constitui um requisito para a avaliação da dimensão D3. Embora o título do recurso sugira uma cobertura temporal referente ao ano de 2023, a ausência de metadados específicos sobre a periodicidade impede a verificação do cumprimento de qualquer cronograma de atualização. A métrica DGABr estabelece que o Nível 0 deve ser atribuído quando não há definição para o item avaliado. Uma vez que não foi identificada uma frequência de atualização estabelecida no PDA ou nos metadados do próprio conjunto de dados, a conformidade com este critério não pode ser aferida. Por essa razão, atribui-se o Nível 0 à dimensão. | G4: =E4*D4 -> 0
A5: Dados Abertos | B5: D4 | C5: Dados acessíveis | D5: 1 | E5: 5 | F5: Verificou-se que o conjunto de dados é acessível publicamente por meio de interface web, que permite o download direto dos arquivos, e de forma programática, via API. A consulta aos endpoints confirmou que ambos os métodos de acesso são disponibilizados sem a exigência de qualquer forma de autenticação, como cadastro ou login, para a obtenção dos dados. A disponibilização do conjunto de dados via web e por meio de API, sem barreiras de identificação, atende integralmente aos critérios da dimensão D4. Essa conformidade fundamenta a atribuição do Nível 5, que corresponde ao cumprimento de 100% dos requisitos estabelecidos pela métrica DGABr 2.0 para esta dimensão. | G5: =E5*D5 -> 5
A6: Dados Abertos | B6: D5 | C6: Dados processados por máquina | D6: 1 | E6: 5 | F6: A análise do conjunto de dados, acessado tanto por download de arquivos quanto via API, constatou a disponibilização em formatos estruturados (CSV e JSON), os quais são nativamente processáveis por máquina. A verificação dos recursos confirmou que os formatos seguem especificações técnicas alinhadas aos ePing. Diante da conformidade integral (100%) dos dados com os padrões técnicos exigidos, atribui-se o Nível 5. Esta avaliação alinha-se aos critérios da DGABr 2.0 para a dimensão D5, que estipula a aderência a especificações do ePING como requisito para os níveis de maior maturidade. | G6: =E6*D6 -> 5
A7: Dados Abertos | B7: D6 | C7: Acesso não discriminatório | D7: 1 | E7: 5 | F7: A análise do conjunto de dados demonstrou que o acesso aos recursos é público e irrestrito, tanto por meio da página web do dataset quanto via API. Não foi identificada a exigência de cadastro, login ou qualquer outra forma de autenticação para a consulta ou o download dos dados. O cumprimento integral (100%) do requisito de acesso não discriminatório, conforme estipulado pela métrica, fundamenta a atribuição do Nível 5. | G7: =E7*D7 -> 5
A8: Dados Abertos | B8: D7 | C8: Dados não proprietários | D8: 1 | E8: 5 | F8: A análise do conjunto de dados evidencia a disponibilização dos recursos em formatos não proprietários, especificamente em CSV e JSON. Ambos os formatos são reconhecidos como padrões abertos e estão em conformidade com as recomendações da métrica para a dimensão D7. Considerando que todos os recursos do conjunto de dados são oferecidos em formatos que atendem integralmente ao critério, atribui-se o Nível 5. | G8: =E8*D8 -> 5
A9: Dados Abertos | B9: D8 | C9: Dados livres de licença | D9: 1 | E9: 2 | F9: Observa-se que o conjunto de dados utiliza a designação "Outro (Aberta)" no campo de licença. Esta classificação é genérica e não corresponde a um modelo de licenciamento padronizado e reconhecido para dados abertos, como as licenças Creative Commons (CC) ou a Open Data Commons Open Database License (ODbL), que são referenciadas pela métrica. A ausência de um instrumento legal específico impede a definição inequívoca dos termos de uso, modificação e redistribuição, não assegurando a conformidade com os princípios de licenciamento que garantem o reúso com restrições mínimas ou nulas. Diante da evidência, atribui-se o Nível 2 a esta dimensão. A justificativa fundamenta-se no critério da métrica DGABr, segundo o qual este nível se aplica quando uma recomendação existe, neste caso, o uso de licenças abertas padrão, mas a publicação dos dados não segue o que foi definido. A utilização de uma licença não especificada, ainda que nomeada como "aberta", representa uma falha na execução da prática recomendada, comprometendo a segurança jurídica necessária para o reúso efetivo dos dados. | G9: =E9*D9 -> 2
A10: Dados Abertos | B10: D9 | C10: URIs desenhadas | D10: 1 | E10: 2 | F10: A análise das URLs dos recursos associados ao conjunto de dados evidencia a adoção de uma estrutura de nomenclatura padronizada. Existe o uso de identificadores únicos (UUIDs) para o conjunto de dados e para o recurso específico, o que contribui para a estabilidade e persistência do endereço eletrônico. Contudo, a estrutura não é considerada "amigável" ou de fácil memorização, conforme preconizado pela métrica, pois é composta por códigos alfanuméricos extensos. A identificação semântica do conteúdo depende exclusivamente do nome do arquivo ao final da URL, e não de um padrão hierárquico legível em seu caminho. Para a atribuição de um nível em conformidade com a DGABr 2.0, contudo, exige-se, para os níveis 3, 4 e 5, a comprovação de uma "política de gestão e preservação de documentos arquivísticos digitais". Adicionalmente, a análise não registra a verificação da estabilidade e persistência dos links, um componente implícito na avaliação original. Sem a evidência documental da política de preservação e um teste de estabilidade, a atribuição de um nível superior a 2 não pode ser tecnicamente fundamentada. Por isso se atribui o Nível 2. Exemplo de URL do conjunto de dados: "http://dadosabertos.ifmg.edu.br/dataset/8864b0d5-f2c6-4edd-9352-0840d8126ca2/resource/3e81ebd5-7163-4d1f-9a30-c7c4b3b07c11/download/conjunto-de-dados-afastamentos-do-pais-servidores-do-ifmg-2023.csv" | G10: =E10*D10 -> 2
A11: Dados Abertos | B11: D10 | C11: Dados ligados | D11: 1 | E11: 0 | F11: A análise do conjunto de dados indica a ausência de vínculos com fontes de dados externas que permitam a contextualização das informações, conforme preconizado pelo princípio de dados ligados (linked data). Não foram identificadas referências, como o uso de RDF (Resource Description Framework) ou outras tecnologias semânticas, que conectem os registros a outros vocabulários ou conjuntos de dados. De acordo com a estrutura da métrica DGABr, a não implementação do item avaliado na dimensão D10 justifica a atribuição do Nível 0. | G11: =E11*D11 -> 0
A12: Legal | B12: D11 | C12: Tipo de informação | D12: 3 | E12: 5 | F12: A dimensão D11 da métrica DGABr analisa se a informação disponibilizada possui respaldo na legislação e nos instrumentos normativos que regulam sua publicação. No caso dos dados referentes aos "afastamentos do país de servidores do IFMG em 2023", trata-se de informação prevista na legislação brasileira, em especial nos artigos 7º e 8º da Lei de Acesso à Informação, que determinam a divulgação ativa desse tipo de dado. Dessa forma, o conjunto atende plenamente ao requisito estabelecido, alcançando o nível 5 na dimensão. | G12: =E12*D12 -> 15
A13: Legal | B13: D12 | C13: Gestão de dados sensíveis | D13: 3 | E13: 4 | F13: O conjunto de dados contém informações de natureza pessoal, como o nome de servidores, o período de afastamento e o respectivo destino. Tais dados, embora referentes a indivíduos identificados, são considerados de interesse público no contexto de servidores federais, em conformidade com a LAI. Adicionalmente, a LGPD permite o tratamento de dados pessoais de acesso público. O órgão publicador não classificou as informações como sigilosas, disponibilizando-as integralmente com base neste enquadramento legal. Atribui-se o Nível 4 a esta dimensão. A pontuação se fundamenta na adequação da publicação à legislação vigente, que ampara a divulgação dos dados. No entanto, a ausência de evidência documental que formalize a estratégia institucional para o tratamento e a dessensibilização de dados pessoais impede a atribuição do nível máximo, que pressupõe o cumprimento integral e documentado dos procedimentos de gestão de dados sensíveis. | G13: =E13*D13 -> 12
... A29: Reúso | B29: D28 | C29: Informações sobre o reúso de DGA | D29: 3 | E29: 0 | F29: A verificação não identificou aplicações, produtos ou serviços que reutilizem o conjunto de dados em análise. A busca por evidências, incluindo a consulta ao registro de reúso no Portal Brasileiro de Dados Abertos, não localizou qualquer produto derivado que permitisse a avaliação dos critérios desta dimensão. A dimensão D28 avalia se as aplicações que reutilizam os DGA informam adequadamente sobre as fontes de dados utilizadas. Dada a ausência de um objeto de análise, a verificação deste critério torna-se inviável. Consequentemente, atribui-se o Nível 0, pois a condição precedente para a avaliação, a existência de ao menos uma aplicação que reutilize o conjunto de dados, não foi satisfeita, conforme a definição da métrica. | G29: =E29*D29 -> 0
A30: Total de Pontos | G30: =SUM(G2:G29) -> 129
A31: Indicador de reúso | G31: =IF(G30<54,1,IF(G30<108,2,IF(G30<162,3,IF(G30<216,4,5)))) -> 3
A32: URL Portal próprio | D32: https://dadosabertos.ifmg.edu.br/dataset/afastamentos-do-pais-dos-servidores-do-ifmg-2023
A33: URL Portal Brasileiro de Dados Abertos | D33: https://dados.gov.br/dados/conjuntos-dados/afastamentos-do-pais-dos-servidores-do-ifmg-2023
A34: URL API | D34: https://dadosabertos.ifmg.edu.br/api/action/package_show?id=afastamentos-do-pais-dos-servidores-do-ifmg-2023

Sheet afastamentos-do-pais-dos-2024
A1: Perspectiva | B1: ID | C1: Dimensão | D1: Peso | E1: Nível (0-5) | F1: Itens Observados | G1: Total
A2: Dados Abertos | B2: D1 | C2: Dados completos | D2: 1 | E2: 0 | F2: A análise do conjunto de dados "Afastamentos do País dos Servidores do IFMG 2024" constatou que este não consta no PDA da instituição. A ausência de menção no referido plano inviabiliza a verificação da completude dos dados, uma vez que não há um parâmetro de referência oficial que defina o escopo esperado para o conjunto, como a totalidade das variáveis ou a abrangência da série histórica planejada. Conforme a metodologia da métrica DGABr, a ausência de uma definição formal para o item avaliado no planejamento institucional impede a aferição do seu cumprimento. Portanto, atribui-se o Nível 0 a esta dimensão. A justificativa para esta classificação reside na impossibilidade técnica de avaliar se os dados publicados atingem os patamares de execução sem um compromisso previamente documentado. | G2: =E2*D2 -> 0
A3: Dados Abertos | B3: D2 | C3: Dados primários | D3: 1 | E3: 5 | F3: A análise do conjunto de dados indica que sua origem é o Sistema Eletrônico de Informações (SEI), com as portarias originais disponíveis para verificação na Imprensa Nacional. O conjunto preserva integralmente as informações da fonte, sem a aplicação de agregações ou modificações que alterem sua granularidade. A estrutura dos dados publicados limita-se a identificar a origem e a extrair os elementos textuais das portarias. Conforme a definição da dimensão D2 da métrica DGABr, que avalia se os dados são brutos e coletados na fonte, o conjunto atende a 100% do critério estabelecido. A ausência de processamento que modifique o conteúdo original fundamenta a atribuição do Nível 5. Registra-se, como uma observação não impeditiva para esta dimensão, a ausência do referido conjunto de dados no PDA, o que aponta para uma lacuna no planejamento formal da publicação. | G3: =E3*D3 -> 5
A4: Dados Abertos | B4: D3 | C4: Dados atualizados / DGA atualizado | D4: 1 | E4: 0 | F4: A análise documental indica que o conjunto de dados em questão não consta no PDA. Consequentemente, não há uma frequência de atualização formalmente definida para este item, um requisito central para a avaliação da dimensão D3 (Dados atualizados). A ausência de metadados que especifiquem a periodicidade no próprio recurso corrobora essa lacuna de informação, impossibilitando a verificação do seu cumprimento. Diante da inexistência de um parâmetro de atualização para aferição, atribui-se o Nível 0. A justificativa alinha-se à definição da métrica para este nível, que se aplica quando "não há definição para o item avaliado". Sem uma periodicidade estabelecida, a avaliação do cumprimento da dimensão torna-se tecnicamente inviável. | G4: =E4*D4 -> 0
A5: Dados Abertos | B5: D4 | C5: Dados acessíveis | D5: 1 | E5: 5 | F5: O acesso ao conjunto de dados ocorre de forma pública via web, não sendo exigido cadastro, login ou qualquer outra forma de identificação para o seu download. Adicionalmente, foi confirmada a disponibilização de uma API, o que viabiliza o consumo automatizado dos dados por sistemas externos. O conjunto dessas evidências demonstra o cumprimento integral dos critérios estabelecidos pela métrica para a dimensão D4. A ausência de barreiras de acesso, tanto para consulta manual quanto para processamento por máquina, justifica a atribuição do Nível 5, em conformidade com a definição de que 100% dos dados devem ser disponibilizados sem restrições de acesso. | G5: =E5*D5 -> 5
A6: Dados Abertos | B6: D5 | C6: Dados processados por máquina | D6: 1 | E6: 5 | F6: A análise do conjunto de dados indica que os recursos são disponibilizados em formatos estruturados (CSV e JSON), os quais são nativamente processáveis por máquina. A avaliação desta dimensão, conforme a DGABr 2.0, requer, para os níveis superiores, a conformidade com as especificações técnicas do ePING. A verificação dos arquivos confirma que os formatos empregados estão em conformidade com o referido padrão. Considerando que a totalidade dos dados atende aos critérios de estruturação e ao padrão de interoperabilidade, atribui-se o Nível 5, em alinhamento com a definição de cumprimento integral da métrica. | G6: =E6*D6 -> 5
A7: Dados Abertos | B7: D6 | C7: Acesso não discriminatório | D7: 1 | E7: 5 | F7: A verificação do conjunto de dados confirmou que o acesso aos recursos é público e irrestrito, realizado tanto por meio de interface web quanto via API. A análise dos pontos de acesso indicados demonstrou a ausência de qualquer exigência de cadastro, login ou outra forma de identificação para o download dos dados. Essa condição caracteriza o acesso como não discriminatório, em total alinhamento com os preceitos da dimensão D6. O cumprimento integral do requisito, ao disponibilizar os dados sem barreiras para qualquer usuário, fundamenta a atribuição do Nível 5. | G7: =E7*D7 -> 5
A8: Dados Abertos | B8: D7 | C8: Dados não proprietários | D8: 1 | E8: 5 | F8: A análise do conjunto de dados indica que os arquivos são disponibilizados nos formatos CSV e JSON. Ambos os formatos são classificados como não proprietários, em conformidade com os critérios estabelecidos pela métrica DGABr para a dimensão D7. Uma vez que 100% dos formatos oferecidos atendem ao requisito, atribui-se o Nível 5, que corresponde ao cumprimento integral do padrão avaliado. | G8: =E8*D8 -> 5
A9: Dados Abertos | B9: D8 | C9: Dados livres de licença | D9: 1 | E9: 2 | F9: Observa-se que o conjunto de dados utiliza a designação "Outro (Aberta)" no campo de licença. Esta classificação é genérica e não corresponde a um modelo de licenciamento padronizado e reconhecido para dados abertos, como as licenças Creative Commons (CC) ou a Open Data Commons Open Database License (ODbL), que são referenciadas pela métrica. A ausência de um instrumento legal específico impede a definição inequívoca dos termos de uso, modificação e redistribuição, não assegurando a conformidade com os princípios de licenciamento que garantem o reúso com restrições mínimas ou nulas. Diante da evidência, atribui-se o Nível 2 a esta dimensão. A justificativa fundamenta-se no critério da métrica DGABr, segundo o qual este nível se aplica quando uma recomendação existe, neste caso, o uso de licenças abertas padrão, mas a publicação dos dados não segue o que foi definido. A utilização de uma licença não especificada, ainda que nomeada como "aberta", representa uma falha na execução da prática recomendada, comprometendo a segurança jurídica necessária para o reúso efetivo dos dados. | G9: =E9*D9 -> 2
A10: Dados Abertos | B10: D9 | C10: URIs desenhadas | D10: 1 | E10: 2 | F10: A análise das URLs dos recursos associados ao conjunto de dados evidencia a adoção de uma estrutura de nomenclatura padronizada. Existe o uso de identificadores únicos (UUIDs) para o conjunto de dados e para o recurso específico, o que contribui para a estabilidade e persistência do endereço eletrônico. Contudo, a estrutura não é considerada "amigável" ou de fácil memorização, conforme preconizado pela métrica, pois é composta por códigos alfanuméricos extensos. A identificação semântica do conteúdo depende exclusivamente do nome do arquivo ao final da URL, e não de um padrão hierárquico legível em seu caminho. Para a atribuição de um nível em conformidade com a DGABr 2.0, contudo, exige-se, para os níveis 3, 4 e 5, a comprovação de uma "política de gestão e preservação de documentos arquivísticos digitais". Adicionalmente, a análise não registra a verificação da estabilidade e persistência dos links, um componente implícito na avaliação original. Sem a evidência documental da política de preservação e um teste de estabilidade, a atribuição de um nível superior a 2 não pode ser tecnicamente fundamentada. Por isso se atribui o Nível 2. Exemplo de URL do conjunto de dados: "http://dadosabertos.ifmg.edu.br/dataset/3b978d5f-443c-4784-8d65-f1aa04b78e16/resource/64fc2fdc-dcda-4aea-975f-689c11cacdf5/download/conjunto-de-dados-afastamentos-do-pais-dos-servidores-do-ifmg-2024.json" | G10: =E10*D10 -> 2
A11: Dados Abertos | B11: D10 | C11: Dados ligados | D11: 1 | E11: 0 | F11: A análise do conjunto de dados indica a ausência de vínculos com fontes de dados externas que permitam a contextualização das informações, conforme preconizado pelo princípio de dados ligados (linked data). Não foram identificadas referências, como o uso de RDF (Resource Description Framework) ou outras tecnologias semânticas, que conectem os registros a outros vocabulários ou conjuntos de dados. De acordo com a estrutura da métrica DGABr, a não implementação do item avaliado na dimensão D10 justifica a atribuição do Nível 0. | G11: =E11*D11 -> 0
A12: Legal | B12: D11 | C12: Tipo de informação | D12: 3 | E12: 5 | F12: A dimensão D11 da métrica DGABr analisa se a informação disponibilizada possui respaldo na legislação e nos instrumentos normativos que regulam sua publicação. No caso dos dados referentes aos "afastamentos do país de servidores do IFMG em 2024", trata-se de informação prevista na legislação brasileira, em especial nos artigos 7º e 8º da Lei de Acesso à Informação, que determinam a divulgação ativa desse tipo de dado. Dessa forma, o conjunto atende plenamente ao requisito estabelecido, alcançando o nível 5 na dimensão. | G12: =E12*D12 -> 15
A13: Legal | B13: D12 | C13: Gestão de dados sensíveis | D13: 3 | E13: 4 | F13: O conjunto de dados contém informações de natureza pessoal, como o nome de servidores, períodos de afastamento e destinos. Contudo, a divulgação de tais informações é amparada pela Lei de Acesso à Informação (Lei n.º 12.527/2011), que estabelece o princípio da publicidade para dados de interesse coletivo, e pela Lei Geral de Proteção de Dados (Lei n.º 13.709/2018), que permite o tratamento de dados pessoais de acesso público. O órgão publicador, ao disponibilizar o conjunto, não o classificou sob regime de sigilo, tratando-o como informação pública. Atribui-se o Nível 4 a esta dimensão. A justificativa fundamenta-se na observação de que o conjunto de dados não contém informações classificadas como sigilosas, e os dados pessoais presentes são considerados de interesse público, o que atende parcialmente aos critérios da dimensão. No entanto, a ausência de documentação que evidencie a estratégia formal de tratamento ou os protocolos de segurança adotados para a gestão desses dados impede a atribuição do Nível 5. Esta lacuna na apresentação do processo de análise e proteção de dados justifica uma avaliação inferior à máxima. | G13: =E13*D13 -> 12
... A29: Reúso | B29: D28 | C29: Informações sobre o reúso de DGA | D29: 3 | E29: 0 | F29: A verificação no Portal Brasileiro de Dados Abertos não indicou a existência de produtos, serviços ou aplicações que reutilizem o conjunto de dados em análise. Conforme a definição da métrica DGABr, a dimensão D28 avalia se os produtos resultantes do reúso informam adequadamente sobre as fontes de DGA utilizadas. Dada a ausência de evidências de reúso, o critério de avaliação para esta dimensão torna-se inaplicável. Por conseguinte, atribui-se o Nível 0, em conformidade com o protocolo da métrica para situações em que o item avaliado não se manifesta. | G29: =E29*D29 -> 0
A30: Total de Pontos | G30: =SUM(G2:G29) -> 129
A31: Indicador de reúso | G31: =IF(G30<54,1,IF(G30<108,2,IF(G30<162,3,IF(G30<216,4,5)))) -> 3
A32: URL Portal próprio | D32: https://dadosabertos.ifmg.edu.br/dataset/afastamentos_do_pais_dos_servidores_do_ifmg_2024_
A33: URL Portal Brasileiro de Dados Abertos | D33: https://dados.gov.br/dados/conjuntos-dados/afastamentos_do_pais_dos_servidores_do_ifmg_2024_
A34: URL API | D34: https://dadosabertos.ifmg.edu.br/api/action/package_show?id=afastamentos_do_pais_dos_servidores_do_ifmg_2024_

Sheet candidatos-e-vagas-tecnico
A1: Perspectiva | B1: ID | C1: Dimensão | D1: Peso | E1: Nível (0-5) | F1: Itens Observados | G1: Total
A2: Dados Abertos | B2: D1 | C2: Dados completos | D2: 1 | E2: 0 | F2: O conjunto de dados “Candidatos e Vagas nos Processos Seletivos de Cursos Técnicos” apresenta informações referentes ao ano de 2024, abrangendo o primeiro e o segundo semestres. A avaliação da completude, conforme a métrica DGABr, incide sobre a abrangência do escopo publicado em relação ao que foi definido no PDA. A ausência de dados de períodos subsequentes, embora a frequência de atualização definida seja semestral, constitui uma evidência primária para a avaliação da dimensão D3 (Dados atualizados). De forma análoga, a publicação de quantitativos consolidados, em vez de dados brutos, afeta diretamente a dimensão D2 (Dados primários), que mensura a granularidade da informação. Para a dimensão D1, a evidência indica a publicação de um subconjunto temporal (ano de 2024). A ausência de detalhamento granular também impede a verificação da completude em outras variáveis. Diante dessas limitações , tanto pela incompletude temporal quanto pela agregação das informações, o conjunto de dados não atende aos critérios mínimos de completude e atualidade, o nível da dimensão é 0, já que o órgão somente publica os DGA sem validar sua completude | G2: =E2*D2 -> 0
A3: Dados Abertos | B3: D2 | C3: Dados primários | D3: 1 | E3: 0 | F3: O conjunto de dados analisado, embora gerado pela unidade institucionalmente responsável (Diretoria de Processos Seletivos), é disponibilizado em formato agregado. Esta característica contraria o critério fundamental da dimensão D2, que, conforme a métrica DGABr, avalia se os dados são brutos, ou seja, coletados na fonte e mantidos com o máximo nível de granularidade, sem modificações ou sumarizações. A ausência de dados desagregados impede que o conjunto seja classificado como primário. Diante da não conformidade com o requisito de granularidade, atribui-se o Nível 0 a esta dimensão. A justificativa se fundamenta na constatação de que a agregação, por si só, descaracteriza o dado como primário, independentemente de sua origem ou da ausência de tratamento interpretativo. Não foram apresentadas evidências que descrevam a metodologia de agregação utilizada, o que reforça a avaliação. | G3: =E3*D3 -> 0
A4: Dados Abertos | B4: D3 | C4: Dados atualizados / DGA atualizado | D4: 1 | E4: 3 | F4: O PDA da instituição estabelece uma frequência de atualização semestral para o conjunto de dados "Candidatos e Vagas nos Processos Seletivos de Cursos Técnicos". A verificação do referido conjunto evidencia a publicação dos dados referentes ao primeiro e segundo semestres de 2024. Contudo, no momento da avaliação, não foi identificada a publicação dos dados correspondentes ao primeiro semestre de 2025, que seria o próximo ciclo previsto no cronograma. Considerando o universo de três ciclos de atualização esperados até a data da análise (2024/1, 2024/2 e 2025/1), o cumprimento observado é de dois ciclos, o que corresponde a aproximadamente 67% da meta. Este percentual alinha-se aos critérios da métrica DGABr para o Nível 3, que exige o cumprimento de, no mínimo, 50% dos padrões definidos e é considerado o patamar mínimo para que os DGA possuam potencial de reúso. | G4: =E4*D4 -> 3
A5: Dados Abertos | B5: D4 | C5: Dados acessíveis | D5: 1 | E5: 5 | F5: O conjunto de dados é disponibilizado para acesso público via web, sem a exigência de identificação, cadastro ou qualquer forma de registro. A verificação confirmou, adicionalmente, a viabilidade de acesso programático por meio de uma API, permitindo a extração automatizada dos dados. A conformidade integral com os requisitos da dimensão D4, que preconiza o acesso irrestrito, fundamenta a atribuição do Nível 5, uma vez que 100% dos critérios definidos pela métrica foram atendidos. | G5: =E5*D5 -> 5
A6: Dados Abertos | B6: D5 | C6: Dados processados por máquina | D6: 1 | E6: 5 | F6: A análise do conjunto de dados evidencia que os recursos são disponibilizados em formatos estruturados (CSV e JSON), o que permite o processamento automatizado por máquina, atendendo ao critério fundamental da dimensão D5. Adicionalmente, a observação de conformidade com as especificações técnicas do ePING alinha a publicação aos requisitos complementados na DGABr 2.0, que estipula tal adequação como um indicador para os níveis de avaliação mais elevados. Pressupondo que 100% dos recursos do conjunto de dados cumprem integralmente os padrões mencionados, atribui-se o Nível 5, por satisfazer plenamente os critérios de estruturação e de alinhamento aos padrões de interoperabilidade governamentais. | G6: =E6*D6 -> 5
A7: Dados Abertos | B7: D6 | C7: Acesso não discriminatório | D7: 1 | E7: 5 | F7: Verifica-se que o conjunto de dados cumpre integralmente os requisitos da dimensão D6 (Acesso não discriminatório), o que justifica a atribuição do Nível 5. A evidência demonstra que o acesso aos recursos é público e realizado via web, não sendo exigido qualquer tipo de cadastro, autenticação ou registro prévio para a sua consulta ou download. A disponibilidade estende-se tanto à interface do portal de dados quanto ao acesso programático por meio de API, garantindo que não existam barreiras técnicas ou administrativas que restrinjam o uso. Esta conformidade alinha-se à definição da métrica DGABr, que estipula a disponibilidade dos dados a todos os usuários, sem barreiras de identificação, como critério para o cumprimento integral da dimensão. | G7: =E7*D7 -> 5
A8: Dados Abertos | B8: D7 | C8: Dados não proprietários | D8: 1 | E8: 5 | F8: A verificação dos recursos do conjunto de dados, acessados tanto por download direto quanto via API, confirma a disponibilização nos formatos CSV e JSON. Ambos são classificados como não proprietários e estão em conformidade com os critérios da dimensão D7 da métrica DGABr. Uma vez que a totalidade dos formatos ofertados atende ao requisito, atribui-se o Nível 5, que pressupõe o cumprimento integral (100%) do padrão avaliado. | G8: =E8*D8 -> 5
A9: Dados Abertos | B9: D8 | C9: Dados livres de licença | D9: 1 | E9: 2 | F9: Observa-se que o conjunto de dados utiliza a designação "Outro (Aberta)" no campo de licença. Esta classificação é genérica e não corresponde a um modelo de licenciamento padronizado e reconhecido para dados abertos, como as licenças Creative Commons (CC) ou a Open Data Commons Open Database License (ODbL), que são referenciadas pela métrica. A ausência de um instrumento legal específico impede a definição inequívoca dos termos de uso, modificação e redistribuição, não assegurando a conformidade com os princípios de licenciamento que garantem o reúso com restrições mínimas ou nulas. Diante da evidência, atribui-se o Nível 2 a esta dimensão. A justificativa fundamenta-se no critério da métrica DGABr, segundo o qual este nível se aplica quando uma recomendação existe, neste caso, o uso de licenças abertas padrão, mas a publicação dos dados não segue o que foi definido. A utilização de uma licença não especificada, ainda que nomeada como "aberta", representa uma falha na execução da prática recomendada, comprometendo a segurança jurídica necessária para o reúso efetivo dos dados. | G9: =E9*D9 -> 2
A10: Dados Abertos | B10: D9 | C10: URIs desenhadas | D10: 1 | E10: 2 | F10: A análise das URLs dos recursos associados ao conjunto de dados evidencia a adoção de uma estrutura de nomenclatura padronizada. Existe o uso de identificadores únicos (UUIDs) para o conjunto de dados e para o recurso específico, o que contribui para a estabilidade e persistência do endereço eletrônico. Contudo, a estrutura não é considerada "amigável" ou de fácil memorização, conforme preconizado pela métrica, pois é composta por códigos alfanuméricos extensos. A identificação semântica do conteúdo depende exclusivamente do nome do arquivo ao final da URL, e não de um padrão hierárquico legível em seu caminho. Para a atribuição de um nível em conformidade com a DGABr 2.0, contudo, exige-se, para os níveis 3, 4 e 5, a comprovação de uma "política de gestão e preservação de documentos arquivísticos digitais". Adicionalmente, a análise não registra a verificação da estabilidade e persistência dos links, um componente implícito na avaliação original. Sem a evidência documental da política de preservação e um teste de estabilidade, a atribuição de um nível superior a 2 não pode ser tecnicamente fundamentada. Por isso se atribui o Nível 2. Exemplo de URL do conjunto de dados: "https://dadosabertos.ifmg.edu.br/dataset/8e24ca57-6868-4f37-b268-0d297552bee9/resource/c7c56188-1381-4c62-8b46-abf30c683c7c/download/conjunto-de-dados-candidatos-e-vagas-cursos-tecnicos.html" | G10: =E10*D10 -> 2
A11: Dados Abertos | B11: D10 | C11: Dados ligados | D11: 1 | E11: 0 | F11: A análise do conjunto de dados indica a ausência de vínculos com fontes de dados externas que permitam a contextualização das informações, conforme preconizado pelo princípio de dados ligados (linked data). Não foram identificadas referências, como o uso de RDF (Resource Description Framework) ou outras tecnologias semânticas, que conectem os registros a outros vocabulários ou conjuntos de dados. De acordo com a estrutura da métrica DGABr, a não implementação do item avaliado na dimensão D10 justifica a atribuição do Nível 0. | G11: =E11*D11 -> 0
A12: Legal | B12: D11 | C12: Tipo de informação | D12: 3 | E12: 5 | F12: A dimensão D11 da métrica DGABr analisa se a informação disponibilizada possui respaldo na legislação e nos instrumentos normativos que regulam sua publicação. No caso dos dados referentes aos "Candidatos e Vagas nos Processos Seletivos de Cursos Técnicos", trata-se de informação prevista na legislação brasileira, em especial nos artigos 7º e 8º da Lei de Acesso à Informação, que determinam a divulgação ativa desse tipo de dado. Dessa forma, o conjunto atende plenamente ao requisito estabelecido, alcançando o nível 5 na dimensão. | G12: =E12*D12 -> 15
A13: Legal | B13: D12 | C13: Gestão de dados sensíveis | D13: 3 | E13: 4 | F13: A análise do conjunto de dados indica a ausência de informações classificadas como sensíveis ou pessoais que demandem tratamento de anonimização ou pseudonimização. Conforme a especificação da métrica DGABr para a dimensão D12, a não aplicabilidade do critério, em virtude da natureza dos dados publicados, corresponde ao cumprimento integral da dimensão. Desta forma, atribui-se o Nível 4, já que registra-se, como lacuna de evidência, a ausência de documentação ou metadados que descrevam a política institucional de segurança da informação ou os procedimentos formais para a gestão e tratamento de dados sensíveis. Embora tal ausência não impacte a avaliação deste conjunto de dados específico, ela representa uma limitação na verificação dos processos de governança de dados do órgão. | G13: =E13*D13 -> 12
... A29: Reúso | B29: D28 | C29: Informações sobre o reúso de DGA | D29: 3 | E29: 0 | F29: Não foram identificadas aplicações, produtos ou serviços que reutilizem o conjunto de dados em análise. A ausência de instâncias de reúso, critério avaliado na dimensão D25, impede a verificação da dimensão D28, cujo objetivo é analisar se os produtos gerados informam sobre as fontes de DGA utilizadas e sua frequência de atualização. Uma vez que não existem produtos a serem inspecionados, o objeto de avaliação é considerado inexistente. Consequentemente, atribui-se o Nível 0 a esta dimensão, em conformidade com a estrutura da métrica DGABr, que define este nível para situações em que o item avaliado não se aplica ou não existe. | G29: =E29*D29 -> 0
A30: Total de Pontos | G30: =SUM(G2:G29) -> 135
A31: Indicador de reúso | G31: =IF(G30<54,1,IF(G30<108,2,IF(G30<162,3,IF(G30<216,4,5)))) -> 3
A32: URL Portal próprio | D32: https://dadosabertos.ifmg.edu.br/dataset/candidatos-e-vagas-nos-processos-seletivos-de-cursos-tecnicos
A33: URL Portal Brasileiro de Dados Abertos | D33: https://dados.gov.br/dados/conjuntos-dados/candidatos-e-vagas-nos-processos-seletivos-de-cursos-tecnicos
A34: URL API | D34: https://dadosabertos.ifmg.edu.br/api/action/package_show?id=candidatos-e-vagas-nos-processos-seletivos-de-cursos-tecnicos

Sheet dados-abertos-projetos-extensao
A1: Perspectiva | B1: ID | C1: Dimensão | D1: Peso | E1: Nível (0-5) | F1: Itens Observados | G1: Total
A2: Dados Abertos | B2: D1 | C2: Dados completos | D2: 1 | E2: 2 | F2: O conjunto de dados "Quantitativo de projetos e bolsas de Extensão" disponibiliza informações referentes ao ano de 2024. Conforme o PDA da instituição, que estabelece o compromisso de publicação para o período de 2023 a 2025 com frequência semestral, constata-se a ausência dos dados relativos ao ano de 2023/1, 20223/2, 2024/2 e 2025/1. A não publicação de um dos dois anos previstos até a data da avaliação configura um cumprimento parcial da completude da série histórica. É importante destacar que o PDA apresenta dois conjuntos distintos, um relacionado aos projetos de extensão e outro às bolsas, cada qual com frequência de atualização própria. O conjunto de projetos de extensão possui atualização anual, enquanto o de bolsas é atualizado semestralmente. Para fins de análise, considerou-se o conjunto com a frequência de atualização mais elevada. Esta lacuna representa a disponibilização de 20% dos dados esperados, o que fundamenta a atribuição do Nível 2. De acordo com a estrutura da métrica DGABr, este nível é aplicado quando a instituição cumpre, no mínimo, 20% dos padrões definidos para a dimensão avaliada, sendo considerado o patamar mínimo para o reúso dos dados. | G2: =E2*D2 -> 2
A3: Dados Abertos | B3: D2 | C3: Dados primários | D3: 1 | E3: 0 | F3: A análise do conjunto de dados indica que, embora sejam extraídos diretamente do sistema SUAP IFMG, os dados são publicados em formato agregado. Evidencia-se tal agregação na apresentação do quantitativo de bolsistas, em detrimento da disponibilização de registros individualizados. Esta característica contraria o critério da dimensão D2, que define dados primários como aqueles com granularidade máxima e isentos de modificações ou agregações. A ausência de dados em sua forma bruta e desagregada fundamenta a atribuição do Nível 0, conforme a definição da métrica DGABr para o não cumprimento do requisito avaliado. A documentação consultada não apresenta justificativa técnica para a agregação dos dados. | G3: =E3*D3 -> 0
A4: Dados Abertos | B4: D3 | C4: Dados atualizados / DGA atualizado | D4: 1 | E4: 2 | F4: Com base na análise do PDA e do conjunto de dados referenciado, observa-se uma divergência entre a periodicidade de atualização definida e a prática de publicação. O PDA institucional estabelece um cronograma que previa a atualização dos dados em 2023. Contudo, a verificação do conjunto de dados indica que tal atualização não foi executada conforme o planejado, com os registros mais recentes datando de 2024, o que evidencia uma defasagem em relação à meta estabelecida. A atribuição do Nível 2 para a dimensão D3 (Dados atualizados) fundamenta-se diretamente nos critérios da métrica DGABr. A existência de uma norma formal , o cronograma de atualização no PDA , que não é cumprida na prática caracteriza esta condição. A situação descrita corresponde à definição do Nível 2, no qual a instituição possui uma recomendação definida, mas a publicação dos dados não segue os prazos e compromissos firmados. | G4: =E4*D4 -> 2
A5: Dados Abertos | B5: D4 | C5: Dados acessíveis | D5: 1 | E5: 5 | F5: A análise do conjunto de dados evidencia que o acesso é público e irrestrito, sendo realizado via web sem a exigência de cadastro, login ou qualquer outra forma de identificação. A acessibilidade é provida tanto por meio de download direto dos arquivos quanto de forma programática, através de uma API, cujo ponto de acesso foi validado no endereço `https://dadosabertos.ifmg.edu.br/api/action/package_show?id=dados-abertos-projetos-extensao-ifmg`. A condição de acesso sem barreiras atende integralmente (100%) aos critérios estabelecidos pela métrica para a dimensão D4 (Dados acessíveis). Consequentemente, atribui-se o Nível 5, uma vez que a disponibilização dos dados ocorre sem qualquer forma de acesso discriminatório ou necessidade de identificação, conforme estipulado para a pontuação máxima nesta dimensão. | G5: =E5*D5 -> 5
A6: Dados Abertos | B6: D5 | C6: Dados processados por máquina | D6: 1 | E6: 2 | F6: Constata-se que o conjunto de dados foi disponibilizado em formato XLSX. Embora se trate de um formato estruturado, que viabiliza um processamento básico por máquina, ele não atende às especificações técnicas previstas no padrão ePING. Diante desse cenário, atribui-se o nível 2, conforme definido pela métrica DGABr, pois o conjunto não cumpre plenamente os requisitos estabelecidos, ainda que o PDA registre a orientação para que os dados sigam o padrão ePING. | G6: =E6*D6 -> 2
A7: Dados Abertos | B7: D6 | C7: Acesso não discriminatório | D7: 1 | E7: 5 | F7: A análise do conjunto de dados evidencia que o acesso aos recursos é público e irrestrito, sendo disponibilizado tanto por meio de uma interface web quanto via API. A verificação dos pontos de acesso indicados confirmou que não há exigência de cadastro, login ou qualquer outra forma de autenticação para a consulta ou download dos dados. O cenário observado representa o cumprimento integral (100%) dos critérios estabelecidos para a dimensão D6, que avalia a disponibilidade dos dados a todos os usuários sem a imposição de barreiras. Em conformidade com a estrutura da métrica DGABr 2.0, que define o atendimento completo dos requisitos como o patamar mais elevado, atribui-se o Nível 5. | G7: =E7*D7 -> 5
A8: Dados Abertos | B8: D7 | C8: Dados não proprietários | D8: 1 | E8: 2 | F8: A análise do conjunto de dados revela uma inconsistência entre os formatos de arquivo declarados nos metadados e o recurso efetivamente disponibilizado. Embora o portal de dados e a API informem a existência de arquivos nos formatos não proprietários CSV e JSON, a verificação empírica demonstrou que todos os links de acesso direcionam para um único arquivo no formato XLSX, que é classificado como proprietário. Conforme a estrutura da métrica DGABr, a existência de uma recomendação ou padrão definido pela instituição que não é seguido na publicação dos dados caracteriza o Nível 2. Uma vez que a instituição declara a intenção de publicar em formatos abertos mas, na prática, disponibiliza apenas um formato proprietário, o cumprimento da dimensão é nulo. Desta forma, atribui-se o Nível 2 a esta dimensão, pois a norma estabelecida nos metadatos não foi executada. | G8: =E8*D8 -> 2
A9: Dados Abertos | B9: D8 | C9: Dados livres de licença | D9: 1 | E9: 5 | F9: A análise do conjunto de dados evidencia a aplicação da licença "Outra (Domínio Público)". Esta designação indica que o conteúdo foi disponibilizado sem restrições de direito autoral, permitindo seu reúso, cópia, modificação e redistribuição. Conforme os critérios da dimensão D8 (Dados livres de licença), que avalia se os dados estão isentos de restrições que impeçam o reúso, a adoção do domínio público representa o cumprimento integral do requisito estabelecido pela métrica. Uma vez que a licença declarada assegura a ausência total de restrições de uso, atendendo a 100% do padrão exigido, atribui-se o Nível 5 a esta dimensão. A evidência para esta avaliação consiste na informação de licenciamento explicitada na página de metadados do referido conjunto de dados. | G9: =E9*D9 -> 5
A10: Dados Abertos | B10: D9 | C10: URIs desenhadas | D10: 1 | E10: 2 | F10: A análise das URLs dos recursos associados ao conjunto de dados evidencia a adoção de uma estrutura de nomenclatura padronizada. Existe o uso de identificadores únicos (UUIDs) para o conjunto de dados e para o recurso específico, o que contribui para a estabilidade e persistência do endereço eletrônico. Contudo, a estrutura não é considerada "amigável" ou de fácil memorização, conforme preconizado pela métrica, pois é composta por códigos alfanuméricos extensos e o nome do conjunto de dados não é descrito na URL. A identificação semântica do conteúdo depende exclusivamente do nome do arquivo ao final da URL, e não de um padrão hierárquico legível em seu caminho. Para a atribuição de um nível em conformidade com a DGABr 2.0, contudo, exige-se, para os níveis 3, 4 e 5, a comprovação de uma "política de gestão e preservação de documentos arquivísticos digitais". Adicionalmente, a análise não registra a verificação da estabilidade e persistência dos links, um componente implícito na avaliação original. Sem a evidência documental da política de preservação e um teste de estabilidade, a atribuição de um nível superior a 2 não pode ser tecnicamente fundamentada. Por isso se atribui o Nível 2. Exemplo de URL do conjunto de dados: "http://dadosabertos.ifmg.edu.br/dataset/a43234b0-8c60-4777-8b38-55857ba548ca/resource/ec01ced3-753d-4921-84fd-7cb78496f5cb/download/dados-abertos-25-10-2024.xlsx" | G10: =E10*D10 -> 2
A11: Dados Abertos | B11: D10 | C11: Dados ligados | D11: 1 | E11: 0 | F11: A análise do conjunto de dados indica a ausência de vínculos com fontes de dados externas que permitam a contextualização das informações, conforme preconizado pelo princípio de dados ligados (linked data). Não foram identificadas referências, como o uso de RDF (Resource Description Framework) ou outras tecnologias semânticas, que conectem os registros a outros vocabulários ou conjuntos de dados. De acordo com a estrutura da métrica DGABr, a não implementação do item avaliado na dimensão D10 justifica a atribuição do Nível 0. | G11: =E11*D11 -> 0
A12: Legal | B12: D11 | C12: Tipo de informação | D12: 3 | E12: 5 | F12: A dimensão D11 da métrica DGABr analisa se a informação disponibilizada possui respaldo na legislação e nos instrumentos normativos que regulam sua publicação. No caso dos dados referentes aos "Quantitativo de projetos e bolsas de Extensão", trata-se de informação prevista na legislação brasileira, em especial nos artigos 7º e 8º da Lei de Acesso à Informação, que determinam a divulgação ativa desse tipo de dado. Dessa forma, o conjunto atende plenamente ao requisito estabelecido, alcançando o nível 5 na dimensão. | G12: =E12*D12 -> 15
A13: Legal | B13: D12 | C13: Gestão de dados sensíveis | D13: 3 | E13: 4 | F13: A análise do conjunto de dados indica a ausência de informações de natureza sensível ou pessoal. Conforme a especificação da dimensão D12 da métrica DGABr, a não aplicabilidade do tratamento de dados sensíveis a um conjunto de dados implica a atribuição do nível 4, uma vez que não há requisitos de dessensibilização ou gestão de sigilo a serem cumpridos. A avaliação, portanto, baseia-se na constatação de que o objeto avaliado não contém elementos que demandem tratamento específico de sensibilidade porém, registra-se a ausência de documentação explícita que detalhe a política de segurança ou os critérios utilizados pela instituição para classificar a sensibilidade dos dados, embora tal lacuna não impacte a pontuação desta dimensão no caso em análise. | G13: =E13*D13 -> 12
... A29: Reúso | B29: D28 | C29: Informações sobre o reúso de DGA | D29: 3 | E29: 0 | F29: A avaliação da dimensão D28 (Informações sobre o reúso de DGA) resultou em Nível 0, justificado pela ausência de produtos ou serviços identificados que reutilizem o conjunto de dados em análise. Conforme a definição da métrica DGABr, esta dimensão avalia se as aplicações que consomem os dados informam aos seus usuários sobre as fontes de DGA utilizadas e a frequência de sua atualização. A inexistência de instâncias de reúso, verificada no Portal Brasileiro de Dados Abertos, impede a análise deste critério, caracterizando a condição como "Inexistente". Dessa forma, a atribuição do Nível 0 está alinhada à estrutura da métrica, uma vez que a pré-condição para a avaliação , a existência de uma aplicação que reutilize os dados , não foi atendida. A ausência de evidências de reúso torna, por consequência, inviável a verificação dos requisitos de transparência sobre as fontes de dados, que constituem o foco desta dimensão. | G29: =E29*D29 -> 0
A30: Total de Pontos | G30: =SUM(G2:G29) -> 109
A31: Indicador de reúso | G31: =IF(G30<54,1,IF(G30<108,2,IF(G30<162,3,IF(G30<216,4,5)))) -> 3
A32: URL Portal próprio | D32: https://dadosabertos.ifmg.edu.br/dataset/dados-abertos-projetos-extensao-ifmg
A33: URL Portal Brasileiro de Dados Abertos | D33: https://dados.gov.br/dados/conjuntos-dados/dados-abertos-projetos-extensao-ifmg
A34: URL API | D34: https://dadosabertos.ifmg.edu.br/api/action/package_show?id=dados-abertos-projetos-extensao-ifmg

Sheet dados-abertos-extensao-convenio
A1: Perspectiva | B1: ID | C1: Dimensão | D1: Peso | E1: Nível (0-5) | F1: Itens Observados | G1: Total
A2: Dados Abertos | B2: D1 | C2: Dados completos | D2: 1 | E2: 0 | F2: O conjunto de dados "Convênios do IFMG", constatou que este não consta no PDA da instituição. A ausência de menção no referido plano inviabiliza a verificação da completude dos dados, uma vez que não há um parâmetro de referência oficial que defina o escopo esperado para o conjunto, como a totalidade das variáveis ou a abrangência da série histórica planejada. Conforme a metodologia da métrica DGABr, a ausência de uma definição formal para o item avaliado no planejamento institucional impede a aferição do seu cumprimento. Portanto, atribui-se o Nível 0 a esta dimensão. A justificativa para esta classificação reside na impossibilidade técnica de avaliar se os dados publicados atingem os patamares de execução sem um compromisso previamente documentado. | G2: =E2*D2 -> 0
A3: Dados Abertos | B3: D2 | C3: Dados primários | D3: 1 | E3: 5 | F3: A análise do conjunto de dados indica que a fonte da informação é o sistema SUAP IFMG. Não foram identificados indícios de agregações, sumarizações ou tratamentos interpretativos, o que demonstra que os dados são disponibilizados em sua forma bruta e com granularidade máxima. Esta constatação atende integralmente aos critérios da dimensão D2 (Dados primários), que avalia se os dados são coletados diretamente na fonte, sem modificações. Portanto, a conformidade com o padrão definido justifica a atribuição do Nível 5. Registra-se, contudo, que a publicação deste conjunto de dados não foi localizada no PDA. Embora este fato não impacte a avaliação da dimensão D2, representa uma lacuna de evidência no que tange ao planejamento formal da disponibilização, aspecto pertinente a outras dimensões da métrica, como a D13 (Plano de Dados Abertos) e a D24 (Quantidade de conjuntos de dados publicados). | G3: =E3*D3 -> 5
A4: Dados Abertos | B4: D3 | C4: Dados atualizados / DGA atualizado | D4: 1 | E4: 0 | F4: A análise documental indica que o conjunto de dados em avaliação não consta no PDA da instituição. Adicionalmente, não foi identificada, nos metadados ou na documentação associada, a definição formal da periodicidade de atualização para este conjunto de dados, um requisito central para a avaliação da dimensão D3 (Dados atualizados). A referência ao ano de 2024, embora presente, é insuficiente para estabelecer um cronograma de atualização verificável. Diante da ausência de um compromisso formal de atualização, torna-se inviável a verificação do cumprimento de qualquer periodicidade. Consequentemente, atribui-se o Nível 0, em conformidade com a definição da métrica DGABr, que estabelece este nível para situações em que não há uma norma ou recomendação definida para o item avaliado. | G4: =E4*D4 -> 0
A5: Dados Abertos | B5: D4 | C5: Dados acessíveis | D5: 1 | E5: 5 | F5: Constatou-se que o conjunto de dados é acessível publicamente por meio da web e via API, conforme verificado no endereço `https://dadosabertos.ifmg.edu.br/api/action/package_show?id=dados-abertos-extensao-ifmg`. O acesso aos recursos não requer qualquer forma de identificação, cadastro ou autenticação, o que representa o cumprimento integral (100%) dos critérios estabelecidos pela métrica para esta dimensão. Por conseguinte, atribui-se o Nível 5. | G5: =E5*D5 -> 5
A6: Dados Abertos | B6: D5 | C6: Dados processados por máquina | D6: 1 | E6: 2 | F6: Constata-se que o conjunto de dados foi disponibilizado em formato XLS. Embora se trate de um formato estruturado, que viabiliza um processamento básico por máquina, ele não atende às especificações técnicas previstas no padrão ePING. Diante desse cenário, atribui-se o nível 2, conforme definido pela métrica DGABr, pois o conjunto não cumpre plenamente os requisitos estabelecidos, ainda que o PDA registre a orientação para que os dados sigam o padrão ePING. | G6: =E6*D6 -> 2
A7: Dados Abertos | B7: D6 | C7: Acesso não discriminatório | D7: 1 | E7: 5 | F7: Constatou-se que o conjunto de dados é disponibilizado para acesso público por meio de interface web e via API, conforme verificado nos endereços eletrônicos fornecidos. A análise confirmou que ambos os métodos de acesso não impõem a necessidade de registro, login ou qualquer outra forma de identificação do usuário para o download dos dados. As URLs dos recursos foram validadas e não apresentaram restrições de uso. Com base nessas evidências, atribui-se o Nível 5 a esta dimensão. A justificativa para tal nível reside no cumprimento integral (100%) do critério de acesso não discriminatório, que, segundo a métrica DGABr, é caracterizado pela disponibilidade dos dados a todos os interessados, sem barreiras de acesso. | G7: =E7*D7 -> 5
A8: Dados Abertos | B8: D7 | C8: Dados não proprietários | D8: 1 | E8: 2 | F8: A análise do conjunto de dados revela uma inconsistência entre os formatos de arquivo declarados nos metadados e o recurso efetivamente disponibilizado. Embora o portal de dados e a API informem a existência de arquivos nos formatos não proprietários CSV e JSON, a verificação empírica demonstrou que todos os links de acesso direcionam para um único arquivo no formato XLSX, que é classificado como proprietário. Conforme a estrutura da métrica DGABr, a existência de uma recomendação ou padrão definido pela instituição que não é seguido na publicação dos dados caracteriza o Nível 2. Uma vez que a instituição declara a intenção de publicar em formatos abertos mas, na prática, disponibiliza apenas um formato proprietário, o cumprimento da dimensão é nulo. Desta forma, atribui-se o Nível 2 a esta dimensão, pois a norma estabelecida nos metadados não foi executada. | G8: =E8*D8 -> 2
A9: Dados Abertos | B9: D8 | C9: Dados livres de licença | D9: 1 | E9: 5 | F9: Constata-se que o conjunto de dados foi publicado sob a licença "Outra (Domínio Público)". Essa designação implica a ausência de restrições de direito autoral, permitindo o uso, a cópia, a modificação e a redistribuição do conteúdo sem necessidade de autorização prévia. A dimensão D8 da métrica DGABr avalia especificamente se os dados estão livres de licenças que restrinjam o reúso. A dedicação ao domínio público representa o cumprimento integral (100%) do critério estabelecido para a dimensão, alinhando-se à definição de "Resultados Avançados". Portanto, a atribuição do Nível 5 é tecnicamente fundamentada, uma vez que a licença adotada maximiza o potencial de reúso ao eliminar barreiras de propriedade intelectual. | G9: =E9*D9 -> 5
A10: Dados Abertos | B10: D9 | C10: URIs desenhadas | D10: 1 | E10: 2 | F10: A análise das URLs dos recursos associados ao conjunto de dados evidencia a adoção de uma estrutura de nomenclatura padronizada. Existe o uso de identificadores únicos (UUIDs) para o conjunto de dados e para o recurso específico, o que contribui para a estabilidade e persistência do endereço eletrônico. Contudo, a estrutura não é considerada "amigável" ou de fácil memorização, conforme preconizado pela métrica, pois é composta por códigos alfanuméricos extensos e o nome do conjunto de dados não é descrito na URL. A identificação semântica do conteúdo depende exclusivamente do nome do arquivo ao final da URL, e não de um padrão hierárquico legível em seu caminho. Para a atribuição de um nível em conformidade com a DGABr 2.0, contudo, exige-se, para os níveis 3, 4 e 5, a comprovação de uma "política de gestão e preservação de documentos arquivísticos digitais". Adicionalmente, a análise não registra a verificação da estabilidade e persistência dos links, um componente implícito na avaliação original. Sem a evidência documental da política de preservação e um teste de estabilidade, a atribuição de um nível superior a 2 não pode ser tecnicamente fundamentada. Por isso se atribui o Nível 2. Exemplo de URL do conjunto de dados: "http://dadosabertos.ifmg.edu.br/dataset/30f158c8-7cc3-4588-84be-968c9b494d68/resource/32f225d0-abf9-416a-ae4c-895edcaee430/download/relatorio_convenios-ativos-no-ifmg_ate_25-10-2024.xls" | G10: =E10*D10 -> 2
A11: Dados Abertos | B11: D10 | C11: Dados ligados | D11: 1 | E11: 0 | F11: A análise do conjunto de dados indica a ausência de vínculos com fontes de dados externas que permitam a contextualização das informações, conforme preconizado pelo princípio de dados ligados (linked data). Não foram identificadas referências, como o uso de RDF (Resource Description Framework) ou outras tecnologias semânticas, que conectem os registros a outros vocabulários ou conjuntos de dados. De acordo com a estrutura da métrica DGABr, a não implementação do item avaliado na dimensão D10 justifica a atribuição do Nível 0. | G11: =E11*D11 -> 0
A12: Legal | B12: D11 | C12: Tipo de informação | D12: 3 | E12: 5 | F12: A dimensão D11 da métrica DGABr analisa se a informação disponibilizada possui respaldo na legislação e nos instrumentos normativos que regulam sua publicação. No caso dos dados referentes aos "Convênios do IFMG", trata-se de informação prevista na legislação brasileira, em especial nos artigos 7º e 8º da Lei de Acesso à Informação, que determinam a divulgação ativa desse tipo de dado. Dessa forma, o conjunto atende plenamente ao requisito estabelecido, alcançando o nível 5 na dimensão. | G12: =E12*D12 -> 15
A13: Legal | B13: D12 | C13: Gestão de dados sensíveis | D13: 3 | E13: 4 | F13: A análise do conjunto de dados indica a ausência de informações de natureza sensível ou pessoal. Conforme a especificação da dimensão D12 da métrica DGABr, a não aplicabilidade do tratamento de dados sensíveis a um conjunto de dados implica a atribuição do nível 4, uma vez que não há requisitos de dessensibilização ou gestão de sigilo a serem cumpridos. A avaliação, portanto, baseia-se na constatação de que o objeto avaliado não contém elementos que demandem tratamento específico de sensibilidade porém, registra-se a ausência de documentação explícita que detalhe a política de segurança ou os critérios utilizados pela instituição para classificar a sensibilidade dos dados, embora tal lacuna não impacte a pontuação desta dimensão no caso em análise. | G13: =E13*D13 -> 12
... A29: Reúso | B29: D28 | C29: Informações sobre o reúso de DGA | D29: 3 | E29: 0 | F29: A consulta aos mecanismos de registro de reúso, notadamente no Portal Brasileiro de Dados Abertos, não identificou aplicações, produtos ou serviços que utilizem o conjunto de dados em análise. A inexistência de um produto derivado que reutilize os DGA (condição avaliada na dimensão D25) inviabiliza, por consequência, a análise da dimensão D28, cujo escopo é verificar se tais produtos informam adequadamente sobre as fontes de dados utilizadas. Desta forma, atribui-se o Nível 0, em conformidade com a métrica DGABr, que designa este nível para situações em que o objeto de avaliação não foi localizado ou não se aplica. | G29: =E29*D29 -> 0
A30: Total de Pontos | G30: =SUM(G2:G29) -> 110
A31: Indicador de reúso | G31: =IF(G30<54,1,IF(G30<108,2,IF(G30<162,3,IF(G30<216,4,5)))) -> 3
A32: URL Portal próprio | D32: https://dadosabertos.ifmg.edu.br/dataset/dados-abertos-extensao-ifmg
A33: URL Portal Brasileiro de Dados Abertos | D33: https://dados.gov.br/dados/conjuntos-dados/dados-abertos-extensao-ifmg
A34: URL API | D34: https://dadosabertos.ifmg.edu.br/api/action/package_show?id=dados-abertos-extensao-ifmg

Sheet denuncias-apuradas-pela-correge
A1: Perspectiva | B1: ID | C1: Dimensão | D1: Peso | E1: Nível (0-5) | F1: Itens Observados | G1: Total
A2: Dados Abertos | B2: D1 | C2: Dados completos | D2: 1 | E2: 4 | F2: A análise do conjunto de dados "Denúncias Apuradas pela Corregedoria entre 2018 a 2023" apresentam as informações sobre as denuncias de forma completa de acordo com a avaliação. Porém, conforme estabelecido no PDA da instituição, a frequência de atualização para este conjunto é anual mas, observa-se a ausência dos dados referentes ao ano de 2024, que seriam esperados de acordo com a periodicidade definida. A atribuição do Nível 4 fundamenta-se no critério quantitativo da métrica DGABr para a dimensão D1. A publicação abrange seis dos sete anos previstos na série temporal (2018-2024), o que corresponde a uma completude de aproximadamente 85,7%. Este percentual atende ao limiar mínimo de 80% exigido para o Nível 4. | G2: =E2*D2 -> 4
A3: Dados Abertos | B3: D2 | C3: Dados primários | D3: 1 | E3: 5 | F3: A análise do conjunto de dados indica que as informações foram geradas e publicadas diretamente pelo órgão responsável, sem evidências de tratamento interpretativo ou agregação. Este fato caracteriza os dados como primários, conforme a definição da métrica DGABr 2.0, que preconiza a disponibilização da informação em sua máxima granularidade, tal como coletada na fonte. Visto que o critério é integralmente atendido, atribui-se o Nível 5 a esta dimensão. | G3: =E3*D3 -> 5
A4: Dados Abertos | B4: D3 | C4: Dados atualizados / DGA atualizado | D4: 1 | E4: 4 | F4: Com base na análise do conjunto de dados "Denúncias Apuradas pela Corregedoria entre 2018 a 2023" e do PDA institucional, observa-se que a frequência de atualização definida para o referido conjunto é anual. A documentação disponível abrange os registros de 2018 a 2023, contudo, constata-se a ausência dos dados relativos ao ano de 2024, os quais seriam esperados para manter a conformidade com a periodicidade estabelecida. O cumprimento parcial da frequência de atualização justifica a atribuição do Nível 4. A métrica DGABr 2.0 estipula este nível para dimensões que atingem, no mínimo, 80% de conformidade. Considerando o período de sete anos (2018-2024), a publicação de dados para seis deles representa uma taxa de cumprimento de aproximadamente 85,7%. Este percentual satisfaz o critério para "Resultados Existentes", mas não atinge os 100% necessários para o Nível 5. | G4: =E4*D4 -> 4
A5: Dados Abertos | B5: D4 | C5: Dados acessíveis | D5: 1 | E5: 5 | F5: O conjunto de dados é disponibilizado para acesso público por meio da web, sem a requisição de cadastro, login ou qualquer outra forma de identificação do usuário. A acessibilidade é corroborada pela disponibilização de uma API, conforme verificado no endereço `https://dadosabertos.ifmg.edu.br/api/action/package_show?id=denuncias-apuradas-pela-corregedoria-em-2018a2023`. Com base nestas evidências, atribui-se o Nível 5 à dimensão D4. A justificativa reside no cumprimento integral (100%) do critério de acesso irrestrito, conforme estipulado pela métrica DGABr, que define este nível como a disponibilização de todos os dados via web sem barreiras de identificação. | G5: =E5*D5 -> 5
A6: Dados Abertos | B6: D5 | C6: Dados processados por máquina | D6: 1 | E6: 5 | F6: Constatou-se que o conjunto de dados é disponibilizado em formatos estruturados e processáveis por máquina, especificamente em CSV e por meio de uma API que retorna dados em JSON. A oferta de dados em tais formatos atende aos critérios da dimensão D5 da métrica DGABr 2.0, a qual, para os níveis de avaliação superiores (3 a 5), exige que os dados sigam especificações técnicas dos Padrões de Interoperabilidade do Governo Eletrônico (ePing). A conformidade dos formatos observados com as recomendações do ePing fundamenta a atribuição do Nível 5, indicando o cumprimento integral dos requisitos para esta dimensão. | G6: =E6*D6 -> 5
A7: Dados Abertos | B7: D6 | C7: Acesso não discriminatório | D7: 1 | E7: 5 | F7: A verificação do conjunto de dados demonstrou que o acesso aos recursos é público e irrestrito. Tanto o download direto dos arquivos, a partir da página do conjunto de dados, quanto o consumo de informações por meio da API foram realizados sem a exigência de cadastro, login ou qualquer outra forma de identificação do usuário. Esta constatação atende integralmente aos critérios da dimensão D6 (Acesso não discriminatório), que avalia a disponibilidade dos dados a todos os públicos sem barreiras de registro. Com base na evidência de cumprimento de 100% do requisito, atribui-se o Nível 5. | G7: =E7*D7 -> 5
A8: Dados Abertos | B8: D7 | C8: Dados não proprietários | D8: 1 | E8: 5 | F8: A verificação dos recursos do conjunto de dados, acessados tanto por download direto quanto via API, constatou que as informações são disponibilizadas nos formatos CSV e JSON. Ambos são classificados como não proprietários, em conformidade com as especificações técnicas referenciadas pela métrica (D7, D15). Uma vez que a totalidade dos formatos oferecidos atende ao critério avaliado, atribui-se o Nível 5, que corresponde ao cumprimento integral do requisito. | G8: =E8*D8 -> 5
A9: Dados Abertos | B9: D8 | C9: Dados livres de licença | D9: 1 | E9: 2 | F9: Observa-se que o conjunto de dados utiliza a designação "Outro (Aberta)" no campo de licença. Esta classificação é genérica e não corresponde a um modelo de licenciamento padronizado e reconhecido para dados abertos, como as licenças Creative Commons (CC) ou a Open Data Commons Open Database License (ODbL), que são referenciadas pela métrica. A ausência de um instrumento legal específico impede a definição inequívoca dos termos de uso, modificação e redistribuição, não assegurando a conformidade com os princípios de licenciamento que garantem o reúso com restrições mínimas ou nulas. Diante da evidência, atribui-se o Nível 2 a esta dimensão. A justificativa fundamenta-se no critério da métrica DGABr, segundo o qual este nível se aplica quando uma recomendação existe, neste caso, o uso de licenças abertas padrão, mas a publicação dos dados não segue o que foi definido. A utilização de uma licença não especificada, ainda que nomeada como "aberta", representa uma falha na execução da prática recomendada, comprometendo a segurança jurídica necessária para o reúso efetivo dos dados. | G9: =E9*D9 -> 2
A10: Dados Abertos | B10: D9 | C10: URIs desenhadas | D10: 1 | E10: 2 | F10: A análise das URLs dos recursos associados ao conjunto de dados evidencia a adoção de uma estrutura de nomenclatura padronizada. Existe o uso de identificadores únicos (UUIDs) para o conjunto de dados e para o recurso específico, o que contribui para a estabilidade e persistência do endereço eletrônico. Contudo, a estrutura não é considerada "amigável" ou de fácil memorização, conforme preconizado pela métrica, pois é composta por códigos alfanuméricos extensos. A identificação semântica do conteúdo depende exclusivamente do nome do arquivo ao final da URL, e não de um padrão hierárquico legível em seu caminho. Para a atribuição de um nível em conformidade com a DGABr 2.0, contudo, exige-se, para os níveis 3, 4 e 5, a comprovação de uma "política de gestão e preservação de documentos arquivísticos digitais". Adicionalmente, a análise não registra a verificação da estabilidade e persistência dos links, um componente implícito na avaliação original. Sem a evidência documental da política de preservação e um teste de estabilidade, a atribuição de um nível superior a 2 não pode ser tecnicamente fundamentada. Por isso se atribui o Nível 2. Exemplo de URL do conjunto de dados: "http://dadosabertos.ifmg.edu.br/dataset/1adbc936-ca37-4d53-89dd-35d9a1a015ca/resource/eac533ff-da7b-4a86-a625-f4183cdee582/download/conjunto-de-dados-denuncias-apuradas-pela-corregedoria-em-2019.csv." | G10: =E10*D10 -> 2
A11: Dados Abertos | B11: D10 | C11: Dados ligados | D11: 1 | E11: 0 | F11: A análise do conjunto de dados indica a ausência de vínculos com fontes de dados externas que permitam a contextualização das informações, conforme preconizado pelo princípio de dados ligados (linked data). Não foram identificadas referências, como o uso de RDF (Resource Description Framework) ou outras tecnologias semânticas, que conectem os registros a outros vocabulários ou conjuntos de dados. De acordo com a estrutura da métrica DGABr, a não implementação do item avaliado na dimensão D10 justifica a atribuição do Nível 0. | G11: =E11*D11 -> 0
A12: Legal | B12: D11 | C12: Tipo de informação | D12: 3 | E12: 5 | F12: A dimensão D11 da métrica DGABr analisa se a informação disponibilizada possui respaldo na legislação e nos instrumentos normativos que regulam sua publicação. No caso dos dados referentes as "Denúncias Apuradas pela Corregedoria entre 2018 a 2023", trata-se de informação prevista na legislação brasileira, em especial nos artigos 7º e 8º da Lei de Acesso à Informação, que determinam a divulgação ativa desse tipo de dado. Dessa forma, o conjunto atende plenamente ao requisito estabelecido, alcançando o nível 5 na dimensão. | G12: =E12*D12 -> 15
A13: Legal | B13: D12 | C13: Gestão de dados sensíveis | D13: 3 | E13: 4 | F13: A análise do conjunto de dados indica a ausência de informações de natureza sensível ou pessoal. Conforme a especificação da dimensão D12 da métrica DGABr, a não aplicabilidade do tratamento de dados sensíveis a um conjunto de dados implica a atribuição do nível 4, uma vez que não há requisitos de dessensibilização ou gestão de sigilo a serem cumpridos. A avaliação, portanto, baseia-se na constatação de que o objeto avaliado não contém elementos que demandem tratamento específico de sensibilidade porém, registra-se a ausência de documentação explícita que detalhe a política de segurança ou os critérios utilizados pela instituição para classificar a sensibilidade dos dados, embora tal lacuna não impacte a pontuação desta dimensão no caso em análise. | G13: =E13*D13 -> 12
... A29: Reúso | B29: D28 | C29: Informações sobre o reúso de DGA | D29: 3 | E29: 0 | F29: Não se identificou a existência de aplicações, produtos ou serviços que reutilizem o conjunto de dados em análise. A avaliação desta dimensão (D28) é conceitualmente dependente da prévia identificação de casos de reúso, conforme estabelecido na dimensão D25. Uma vez que não foram localizados exemplos concretos de reutilização, torna-se inviável a verificação do critério central da D28: a comunicação, nos produtos gerados, sobre as fontes de DGA utilizadas e sua frequência de atualização. A ausência de evidências de reúso, que constitui o objeto de análise desta dimensão, fundamenta a atribuição do Nível 0. Esta classificação alinha-se à definição da métrica DGABr, que designa o Nível 0 para situações em que o item avaliado não pode ser observado ou não possui uma definição aplicável ao contexto do conjunto de dados. | G29: =E29*D29 -> 0
A30: Total de Pontos | G30: =SUM(G2:G29) -> 133
A31: Indicador de reúso | G31: =IF(G30<54,1,IF(G30<108,2,IF(G30<162,3,IF(G30<216,4,5)))) -> 3
A32: URL Portal próprio | D32: https://dadosabertos.ifmg.edu.br/dataset/denuncias-apuradas-pela-corregedoria-em-2018a2023
A33: URL Portal Brasileiro de Dados Abertos | D33: https://dados.gov.br/dados/conjuntos-dados/denuncias-apuradas-pela-corregedoria-em-2018a2023
A34: URL API | D34: https://dadosabertos.ifmg.edu.br/api/action/package_show?id=denuncias-apuradas-pela-corregedoria-em-2018a2023

Sheet cursos-tecnicos-ofertados
A1: Perspectiva | B1: ID | C1: Dimensão | D1: Peso | E1: Nível (0-5) | F1: Itens Observados | G1: Total
A2: Dados Abertos | B2: D1 | C2: Dados completos | D2: 1 | E2: 5 | F2: O conjunto de dados "Cursos Técnicos de Nível Médio Ofertados" disponibiliza informações referentes ao ano de 2024. Conforme o PDA do IFMG, a frequência de atualização para este conjunto é anual. A avaliação da dimensão D1 (Dados completos), no entanto, incide sobre a completude do escopo dos dados publicados em relação ao que foi planejado, como a abrangência de séries históricas ou a totalidade das variáveis previstas. Ao que se propõe o conjunto de dados os campos "campus,nome-do-curso,forma-de-oferta,turno-de-oferta,modalidade-de-oferta,vagas-ofertadas" parecem ser completos o suficiente, para o mesmo. Assumindo que o escopo planejado no PDA se limita aos dados do ano vigente, a publicação das informações de 2024 corresponderia a 100% do previsto, o que fundamentaria a atribuição do Nível 5. | G2: =E2*D2 -> 5
A3: Dados Abertos | B3: D2 | C3: Dados primários | D3: 1 | E3: 5 | F3: Observa-se que os dados são provenientes diretamente da unidade organizacional responsável por sua geração, a Diretoria de Processos Seletivos. Não foram identificadas evidências de tratamento interpretativo ou de agregação nas informações disponibilizadas, o que indica que os dados mantêm sua integridade e granularidade originais. Este cenário atende ao critério da dimensão D2, que, segundo a métrica DGABr, avalia se os dados são brutos e coletados na fonte, sem modificações. A conformidade integral com o padrão estabelecido para a dimensão justifica a atribuição do Nível 5. | G3: =E3*D3 -> 5
A4: Dados Abertos | B4: D3 | C4: Dados atualizados / DGA atualizado | D4: 1 | E4: 5 | F4: A avaliação desta dimensão verifica a conformidade entre a frequência de atualização definida no PDA e a temporalidade dos dados efetivamente publicados. O PDA da instituição estabelece uma periodicidade anual para o conjunto de dados "Cursos Técnicos de Nível Médio Ofertados". A inspeção do referido conjunto de dados evidencia que as informações disponibilizadas correspondem ao ano de 2024, o que demonstra o cumprimento integral do cronograma. Diante da correspondência de 100% entre o planejado e o executado, atribui-se o Nível 5 a esta dimensão. A justificativa se fundamenta na observação de que a publicação dos dados atende integralmente à frequência de atualização documentada e que os cursos técnicos de nível médio tem duração anual, o que viabiliza as informações estarem tão atuais quanto necessário, em conformidade com os critérios da métrica. | G4: =E4*D4 -> 5
A5: Dados Abertos | B5: D4 | C5: Dados acessíveis | D5: 1 | E5: 5 | F5: Constata-se que o conjunto de dados é acessível publicamente por meio da web, não exigindo qualquer forma de identificação, cadastro ou login para o seu acesso. Adicionalmente, foi verificada a disponibilização de uma API, que permite o acesso programático aos dados. Tais características cumprem integralmente os requisitos da dimensão D4, que avalia se os dados são acessíveis via web sem barreiras de identificação. A existência de múltiplos meios de acesso, incluindo uma API, evidencia a conformidade total com os padrões definidos pela métrica, o que fundamenta a atribuição do Nível 5. | G5: =E5*D5 -> 5
A6: Dados Abertos | B6: D5 | C6: Dados processados por máquina | D6: 1 | E6: 5 | F6: A análise do conjunto de dados evidencia sua disponibilização em formatos estruturados (JSON e CSV), o que viabiliza o processamento automatizado por máquina. Constatou-se, ademais, a conformidade de tais formatos com as especificações técnicas dos Padrões de Interoperabilidade do Governo Eletrônico (ePing), um requisito introduzido na métrica DGABr 2.0 para os níveis de avaliação superiores desta dimensão. O alinhamento integral aos padrões técnicos recomendados, abrangendo 100% dos formatos disponibilizados, fundamenta a atribuição do Nível 5. Esta classificação corresponde ao cumprimento total dos critérios estabelecidos pela métrica para a dimensão D5, que associa os níveis mais elevados à adesão explícita às especificações do ePing. | G6: =E6*D6 -> 5
A7: Dados Abertos | B7: D6 | C7: Acesso não discriminatório | D7: 1 | E7: 5 | F7: Constatou-se que o acesso ao conjunto de dados é público e irrestrito, sendo disponibilizado tanto por meio de interface web quanto via API. A análise dos pontos de acesso indicados confirmou a ausência de qualquer exigência de cadastro, login ou outra forma de identificação para o download dos recursos. Esta condição atende integralmente ao critério da dimensão D6 (Acesso não discriminatório), que avalia se os dados estão disponíveis para todos os usuários sem barreiras. Em conformidade com a estrutura da métrica, o cumprimento de 100% do requisito corresponde ao Nível 5. A dimensão D6 não sofreu alterações na versão 2.0 da métrica, mantendo-se a avaliação original. Portanto, a evidência descrita fundamenta a atribuição do nível máximo para esta dimensão. | G7: =E7*D7 -> 5
A8: Dados Abertos | B8: D7 | C8: Dados não proprietários | D8: 1 | E8: 5 | F8: A verificação dos arquivos do conjunto de dados, obtidos por download direto e via API, constatou a sua disponibilização nos formatos CSV e JSON. Ambos os formatos são classificados como não proprietários, alinhando-se aos padrões técnicos recomendados pela métrica DGABr. Uma vez que a totalidade dos formatos oferecidos atende ao critério estabelecido, a publicação é considerada integral. Tal conformidade justifica a atribuição do Nível 5, que, segundo a metodologia, corresponde ao cumprimento de 100% do requisito avaliado na dimensão. | G8: =E8*D8 -> 5
A9: Dados Abertos | B9: D8 | C9: Dados livres de licença | D9: 1 | E9: 2 | F9: Observa-se que o conjunto de dados utiliza a designação "Outro (Aberta)" no campo de licença. Esta classificação é genérica e não corresponde a um modelo de licenciamento padronizado e reconhecido para dados abertos, como as licenças Creative Commons (CC) ou a Open Data Commons Open Database License (ODbL), que são referenciadas pela métrica. A ausência de um instrumento legal específico impede a definição inequívoca dos termos de uso, modificação e redistribuição, não assegurando a conformidade com os princípios de licenciamento que garantem o reúso com restrições mínimas ou nulas. Diante da evidência, atribui-se o Nível 2 a esta dimensão. A justificativa fundamenta-se no critério da métrica DGABr, segundo o qual este nível se aplica quando uma recomendação existe, neste caso, o uso de licenças abertas padrão, mas a publicação dos dados não segue o que foi definido. A utilização de uma licença não especificada, ainda que nomeada como "aberta", representa uma falha na execução da prática recomendada, comprometendo a segurança jurídica necessária para o reúso efetivo dos dados. | G9: =E9*D9 -> 2
A10: Dados Abertos | B10: D9 | C10: URIs desenhadas | D10: 1 | E10: 2 | F10: A análise das URLs dos recursos associados ao conjunto de dados evidencia a adoção de uma estrutura de nomenclatura padronizada. Existe o uso de identificadores únicos (UUIDs) para o conjunto de dados e para o recurso específico, o que contribui para a estabilidade e persistência do endereço eletrônico. Contudo, a estrutura não é considerada "amigável" ou de fácil memorização, conforme preconizado pela métrica, pois é composta por códigos alfanuméricos extensos. A identificação semântica do conteúdo depende exclusivamente do nome do arquivo ao final da URL, e não de um padrão hierárquico legível em seu caminho. Para a atribuição de um nível em conformidade com a DGABr 2.0, contudo, exige-se, para os níveis 3, 4 e 5, a comprovação de uma "política de gestão e preservação de documentos arquivísticos digitais". Adicionalmente, a análise não registra a verificação da estabilidade e persistência dos links, um componente implícito na avaliação original. Sem a evidência documental da política de preservação e um teste de estabilidade, a atribuição de um nível superior a 2 não pode ser tecnicamente fundamentada. Por isso se atribui o Nível 2. Exemplo de URL do conjunto de dados: "http://dadosabertos.ifmg.edu.br/dataset/a388d221-708a-427b-9f16-341f9d22e1f1/resource/5b0fcf91-60d0-47ff-b1ac-d6d8a90e85f4/download/conjunto-de-dados-cursos-tecnicos-ofertados.csv" | G10: =E10*D10 -> 2
A11: Dados Abertos | B11: D10 | C11: Dados ligados | D11: 1 | E11: 0 | F11: A análise do conjunto de dados indica a ausência de vínculos com fontes de dados externas que permitam a contextualização das informações, conforme preconizado pelo princípio de dados ligados (linked data). Não foram identificadas referências, como o uso de RDF (Resource Description Framework) ou outras tecnologias semânticas, que conectem os registros a outros vocabulários ou conjuntos de dados. De acordo com a estrutura da métrica DGABr, a não implementação do item avaliado na dimensão D10 justifica a atribuição do Nível 0. | G11: =E11*D11 -> 0
A12: Legal | B12: D11 | C12: Tipo de informação | D12: 3 | E12: 5 | F12: A dimensão D11 da métrica DGABr analisa se a informação disponibilizada possui respaldo na legislação e nos instrumentos normativos que regulam sua publicação. No caso dos dados referentes aos "Cursos Técnicos de Nível Médio Ofertados", trata-se de informação prevista na legislação brasileira, em especial nos artigos 7º e 8º da Lei de Acesso à Informação, que determinam a divulgação ativa desse tipo de dado. Dessa forma, o conjunto atende plenamente ao requisito estabelecido, alcançando o nível 5 na dimensão. | G12: =E12*D12 -> 15
A13: Legal | B13: D12 | C13: Gestão de dados sensíveis | D13: 3 | E13: 4 | F13: A análise do conjunto de dados indica a ausência de informações de natureza sensível ou pessoal. Conforme a especificação da dimensão D12 da métrica DGABr, a não aplicabilidade do tratamento de dados sensíveis a um conjunto de dados implica a atribuição do nível 4, uma vez que não há requisitos de dessensibilização ou gestão de sigilo a serem cumpridos. A avaliação, portanto, baseia-se na constatação de que o objeto avaliado não contém elementos que demandem tratamento específico de sensibilidade porém, registra-se a ausência de documentação explícita que detalhe a política de segurança ou os critérios utilizados pela instituição para classificar a sensibilidade dos dados, embora tal lacuna não impacte a pontuação desta dimensão no caso em análise. | G13: =E13*D13 -> 12
... A29: Reúso | B29: D28 | C29: Informações sobre o reúso de DGA | D29: 3 | E29: 0 | F29: A verificação de instâncias de reúso não identificou produtos, serviços ou aplicações desenvolvidos a partir do conjunto de dados analisado. A dimensão D28, "Informações sobre o reúso de DGA", avalia se os produtos que reutilizam os dados informam aos seus usuários a fonte e a frequência de atualização das informações originais. Visto que a pré-condição para esta avaliação , a existência de ao menos uma aplicação que reutilize os dados (conforme D25) , não foi atendida, a mensuração dos critérios de D28 torna-se inviável. Em conformidade com a estrutura da métrica DGABr, que define o Nível 0 para situações em que o item avaliado não existe ou suas condições de avaliação não são cumpridas, atribui-se este nível à dimensão. A ausência de evidências de reúso impede a análise sobre a qualidade da informação fornecida em produtos derivados, resultando na pontuação mínima. | G29: =E29*D29 -> 0
A30: Total de Pontos | G30: =SUM(G2:G29) -> 145
A31: Indicador de reúso | G31: =IF(G30<54,1,IF(G30<108,2,IF(G30<162,3,IF(G30<216,4,5)))) -> 3
A32: URL Portal próprio | D32: https://dadosabertos.ifmg.edu.br/dataset/cursos-tecnicos-ofertados
A33: URL Portal Brasileiro de Dados Abertos | D33: https://dados.gov.br/dados/conjuntos-dados/candidatos-e-vagas-nos-processos-seletivos-de-cursos-tecnicos
A34: URL API | D34: https://dadosabertos.ifmg.edu.br/api/action/package_show?id=cursos-tecnicos-ofertados.

Sheet cursos-de-graduacao-ofertados
A1: Perspectiva | B1: ID | C1: Dimensão | D1: Peso | E1: Nível (0-5) | F1: Itens Observados | G1: Total
A2: Dados Abertos | B2: D1 | C2: Dados completos | D2: 1 | E2: 5 | F2: O conjunto de dados “Cursos de Graduação Ofertados” reúne informações referentes ao ano de 2024 e está alinhado à frequência anual de atualização definida no PDA do IFMG. Essa conformidade indica que o órgão cumpriu o cronograma previsto para o período. A atribuição do nível 5 para a dimensão D1 (Dados completos) baseia-se na observação de que o escopo correspondente ao ano de 2024 foi integralmente disponibilizado. Os campos apresentados , campus, nome do curso, modalidade do curso, turno de oferta, modalidade de oferta e vagas ofertadas , compõem informações suficientes para caracterizar o conjunto como completo, o que justifica o nível alcançado. | G2: =E2*D2 -> 5
A3: Dados Abertos | B3: D2 | C3: Dados primários | D3: 1 | E3: 5 | F3: A análise do conjunto de dados indica que sua origem é a Diretoria de Processos Seletivos, setor institucionalmente responsável pelo registro das inscrições e pela oferta de vagas. Não foram identificadas evidências de tratamento interpretativo ou de agregação sobre os dados brutos, que são apresentados em sua granularidade máxima. Este fato caracteriza o conjunto como dados primários, em conformidade com a definição da dimensão D2 da métrica DGABr. O cumprimento integral (100%) dos critérios estabelecidos para esta dimensão fundamenta a atribuição do Nível 5. | G3: =E3*D3 -> 5
A4: Dados Abertos | B4: D3 | C4: Dados atualizados / DGA atualizado | D4: 1 | E4: 4 | F4: A análise do PDA da instituição indica frequência anual de atualização para o conjunto “Cursos de Graduação Ofertados”. A verificação do conjunto confirma que as informações disponibilizadas correspondem ao exercício de 2024, demonstrando aderência ao cronograma estabelecido. Embora o órgão tenha cumprido a periodicidade prevista no plano, observa-se que cursos de graduação possuem dinâmica de oferta semestral, o que sugere que a atualização anual não contempla plenamente o potencial informacional do conjunto. Esse descompasso fundamenta a atribuição do Nível 4 para esta dimensão. | G4: =E4*D4 -> 4
A5: Dados Abertos | B5: D4 | C5: Dados acessíveis | D5: 1 | E5: 5 | F5: O acesso ao conjunto de dados ocorre de forma pública via web, não sendo exigido cadastro, login ou qualquer outra forma de identificação para o seu download. Adicionalmente, foi confirmada a disponibilização de uma API, o que viabiliza o consumo automatizado dos dados por sistemas externos. O conjunto dessas evidências demonstra o cumprimento integral dos critérios estabelecidos pela métrica para a dimensão D4. A ausência de barreiras de acesso, tanto para consulta manual quanto para processamento por máquina, justifica a atribuição do Nível 5, em conformidade com a definição de que 100% dos dados devem ser disponibilizados sem restrições de acesso. | G5: =E5*D5 -> 5
A6: Dados Abertos | B6: D5 | C6: Dados processados por máquina | D6: 1 | E6: 5 | F6: A análise do conjunto de dados evidencia que os recursos são disponibilizados em formatos estruturados (CSV e JSON), bem como por meio de uma API, o que atende ao critério fundamental de processamento por máquina. Adicionalmente, a observada conformidade com as especificações técnicas do ePING cumpre o requisito introduzido na métrica DGABr 2.0 para os níveis de avaliação mais elevados. A combinação da oferta de múltiplos formatos estruturados, acesso via API e a aderência aos padrões de interoperabilidade governamentais fundamenta a atribuição de um nível de cumprimento integral para esta dimensão. | G6: =E6*D6 -> 5
A7: Dados Abertos | B7: D6 | C7: Acesso não discriminatório | D7: 1 | E7: 5 | F7: Com base na análise dos pontos de acesso fornecidos, constata-se que o conjunto de dados está disponível publicamente via web e por meio de uma API, sem a requisição de cadastro, login ou qualquer outra forma de autenticação para o acesso aos recursos. A ausência total de barreiras de acesso caracteriza o cumprimento integral do critério de acesso não discriminatório, conforme definido pela dimensão D6 da métrica. Esta observação fundamenta a atribuição do Nível 5 – Resultados Avançados. A métrica DGABr estipula este nível para os casos em que 100% dos dados são disponibilizados sem a necessidade de identificação do usuário, condição plenamente atendida pelo conjunto de dados avaliado. | G7: =E7*D7 -> 5
A8: Dados Abertos | B8: D7 | C8: Dados não proprietários | D8: 1 | E8: 5 | F8: A análise do conjunto de dados constatou que os recursos são disponibilizados nos formatos CSV e JSON. Ambos os formatos são classificados como não proprietários, atendendo integralmente aos critérios estabelecidos pela dimensão D7 da métrica DGABr. A verificação foi realizada por meio da inspeção direta dos arquivos obtidos tanto na página do conjunto de dados quanto via API. Uma vez que a totalidade dos formatos oferecidos cumpre o requisito avaliado, a conformidade é de 100%. De acordo com a estrutura da métrica, o cumprimento integral corresponde ao Nível 5, justificando a atribuição deste nível à dimensão. | G8: =E8*D8 -> 5
A9: Dados Abertos | B9: D8 | C9: Dados livres de licença | D9: 1 | E9: 2 | F9: Observa-se que o conjunto de dados utiliza a designação "Outro (Aberta)" no campo de licença. Esta classificação é genérica e não corresponde a um modelo de licenciamento padronizado e reconhecido para dados abertos, como as licenças Creative Commons (CC) ou a Open Data Commons Open Database License (ODbL), que são referenciadas pela métrica. A ausência de um instrumento legal específico impede a definição inequívoca dos termos de uso, modificação e redistribuição, não assegurando a conformidade com os princípios de licenciamento que garantem o reúso com restrições mínimas ou nulas. Diante da evidência, atribui-se o Nível 2 a esta dimensão. A justificativa fundamenta-se no critério da métrica DGABr, segundo o qual este nível se aplica quando uma recomendação existe, neste caso, o uso de licenças abertas padrão, mas a publicação dos dados não segue o que foi definido. A utilização de uma licença não especificada, ainda que nomeada como "aberta", representa uma falha na execução da prática recomendada, comprometendo a segurança jurídica necessária para o reúso efetivo dos dados. | G9: =E9*D9 -> 2
A10: Dados Abertos | B10: D9 | C10: URIs desenhadas | D10: 1 | E10: 2 | F10: A análise das URLs dos recursos associados ao conjunto de dados evidencia a adoção de uma estrutura de nomenclatura padronizada. Existe o uso de identificadores únicos (UUIDs) para o conjunto de dados e para o recurso específico, o que contribui para a estabilidade e persistência do endereço eletrônico. Contudo, a estrutura não é considerada "amigável" ou de fácil memorização, conforme preconizado pela métrica, pois é composta por códigos alfanuméricos extensos. A identificação semântica do conteúdo depende exclusivamente do nome do arquivo ao final da URL, e não de um padrão hierárquico legível em seu caminho. Para a atribuição de um nível em conformidade com a DGABr 2.0, contudo, exige-se, para os níveis 3, 4 e 5, a comprovação de uma "política de gestão e preservação de documentos arquivísticos digitais". Adicionalmente, a análise não registra a verificação da estabilidade e persistência dos links, um componente implícito na avaliação original. Sem a evidência documental da política de preservação e um teste de estabilidade, a atribuição de um nível superior a 2 não pode ser tecnicamente fundamentada. Por isso se atribui o Nível 2. Exemplo de URL do conjunto de dados: "http://dadosabertos.ifmg.edu.br/dataset/b3c3c917-040e-42f9-bc9a-44769fd13f94/resource/f87bdc76-eb19-4af0-8004-37f8d8e60ad3/download/conjunto-de-dados-cursos-de-graduacao-ofertados.csv" | G10: =E10*D10 -> 2
A11: Dados Abertos | B11: D10 | C11: Dados ligados | D11: 1 | E11: 0 | F11: A análise do conjunto de dados indica a ausência de vínculos com fontes de dados externas que permitam a contextualização das informações, conforme preconizado pelo princípio de dados ligados (linked data). Não foram identificadas referências, como o uso de RDF (Resource Description Framework) ou outras tecnologias semânticas, que conectem os registros a outros vocabulários ou conjuntos de dados. De acordo com a estrutura da métrica DGABr, a não implementação do item avaliado na dimensão D10 justifica a atribuição do Nível 0. | G11: =E11*D11 -> 0
A12: Legal | B12: D11 | C12: Tipo de informação | D12: 3 | E12: 5 | F12: A dimensão D11 da métrica DGABr analisa se a informação disponibilizada possui respaldo na legislação e nos instrumentos normativos que regulam sua publicação. No caso dos dados referentes aos "Cursos de Graduação Ofertados", trata-se de informação prevista na legislação brasileira, em especial nos artigos 7º e 8º da Lei de Acesso à Informação, que determinam a divulgação ativa desse tipo de dado. Dessa forma, o conjunto atende plenamente ao requisito estabelecido, alcançando o nível 5 na dimensão. | G12: =E12*D12 -> 15
A13: Legal | B13: D12 | C13: Gestão de dados sensíveis | D13: 3 | E13: 4 | F13: A análise do conjunto de dados indica a ausência de informações de natureza sensível ou pessoal. Conforme a especificação da dimensão D12 da métrica DGABr, a não aplicabilidade do tratamento de dados sensíveis a um conjunto de dados implica a atribuição do nível 4, uma vez que não há requisitos de dessensibilização ou gestão de sigilo a serem cumpridos. A avaliação, portanto, baseia-se na constatação de que o objeto avaliado não contém elementos que demandem tratamento específico de sensibilidade porém, registra-se a ausência de documentação explícita que detalhe a política de segurança ou os critérios utilizados pela instituição para classificar a sensibilidade dos dados, embora tal lacuna não impacte a pontuação desta dimensão no caso em análise. | G13: =E13*D13 -> 12
... A29: Reúso | B29: D28 | C29: Informações sobre o reúso de DGA | D29: 3 | E29: 0 | F29: A avaliação da dimensão D28 (Informações sobre o reúso de DGA) é dependente da identificação prévia de aplicações que utilizem o conjunto de dados, conforme estipulado na dimensão D25. A consulta aos mecanismos formais de registro, como o Portal Brasileiro de Dados Abertos, não identificou produtos, serviços ou aplicações que façam uso do referido conjunto de dados. A ausência de um caso de reúso documentado impede a verificação do critério central da D28, que consiste em analisar se os produtos gerados informam adequadamente sobre as fontes de DGA utilizadas. Dessa forma, atribui-se o Nível 0 a esta dimensão, uma vez que o objeto de sua análise , um produto derivado do reúso dos dados, não foi localizado. Cabe registrar que esta classificação reflete a ausência de evidência formal de reúso, não sendo possível aferir, por meio deste método, a existência de utilizações não catalogadas. | G29: =E29*D29 -> 0
A30: Total de Pontos | G30: =SUM(G2:G29) -> 146
A31: Indicador de reúso | G31: =IF(G30<54,1,IF(G30<108,2,IF(G30<162,3,IF(G30<216,4,5)))) -> 3
A32: URL Portal próprio | D32: https://dadosabertos.ifmg.edu.br/dataset/cursos-de-graduacao-ofertados
A33: URL Portal Brasileiro de Dados Abertos | D33: https://dados.gov.br/dados/conjuntos-dados/cursos-de-graduacao-ofertados
A34: URL API | D34: https://dadosabertos.ifmg.edu.br/api/action/package_show?id=cursos-de-graduacao-ofertados

Sheet pos_graduacao_lato_sensu
A1: Perspectiva | B1: ID | C1: Dimensão | D1: Peso | E1: Nível (0-5) | F1: Itens Observados | G1: Total
A2: Dados Abertos | B2: D1 | C2: Dados completos | D2: 1 | E2: 1 | F2: A análise do conjunto de dados "Cursos de Pós-Graduação Lato Sensu do IFMG" indica a disponibilização de informações referentes ao ano de 2024, em conformidade com a frequência de atualização anual estabelecida no PDA. Contudo, a dimensão D1 (Dados completos) avalia a completude da série histórica, e não apenas a existência de dados para o período corrente. A ausência de dados de 2025 caracteriza a publicação como um subconjunto do escopo temporal potencial do programa. É importante também salientar que o o conjutno de dados não é completo já que apresenta somente os campos: - Campus, nome do curso e egressos, o que é bem inferior as informações sobre os outros cursos listados em outros conjunto de dados. Considerando que apenas uma fração da série histórica está presente, o critério de completude é atendido de forma parcial. A métrica DGABr estabelece o Nível 1 para o cumprimento o caso em que o orgão somente publica os dados e não possui critérios para avaliar se os mesmos são completos. | G2: =D2*E2 -> 1
A3: Dados Abertos | B3: D2 | C3: Dados primários | D3: 1 | E3: 5 | F3: A análise do conjunto de dados evidencia que as informações são originárias da fonte institucional responsável pelo registro de inscrições e oferta de vagas. Não foram identificadas evidências de tratamento interpretativo ou de agregação, o que alinha o conjunto de dados ao critério de dados primários (D2) da métrica DGABr. Diante da conformidade integral com o critério de granularidade máxima e origem direta da fonte, justifica-se a atribuição do Nível 5. | G3: =D3*E3 -> 5
A4: Dados Abertos | B4: D3 | C4: Dados atualizados / DGA atualizado | D4: 1 | E4: 4 | F4: A análise do PDA do IFMG indica que a frequência de atualização estabelecida para o conjunto de dados é anual. Constata-se que o recurso publicado contém informações referentes ao ano de 2024, o que demonstra conformidade com o cronograma definido no plano. A evidência aponta para o cumprimento integral da periodicidade de atualização documentada, que é o critério central de avaliação para a dimensão D3. Embora o órgão tenha cumprido a periodicidade prevista no plano, observa-se que cursos de pós-graduação latu sensu possuem dinâmica de oferta semestral, o que sugere que a atualização anual não contempla plenamente o potencial informacional do conjunto. Esse descompasso fundamenta a atribuição do Nível 4 para esta dimensão. | G4: =D4*E4 -> 4
A5: Dados Abertos | B5: D4 | C5: Dados acessíveis | D5: 1 | E5: 5 | F5: O conjunto de dados é acessível publicamente por meio da web, não requerendo identificação, cadastro ou autenticação para o acesso. Adicionalmente, a disponibilização ocorre por meio de uma API, conforme verificado no endereço eletrônico fornecido, método que viabilizou o download dos arquivos. A evidência observada fundamenta a atribuição do Nível 5 a esta dimensão. Tal classificação se justifica pelo cumprimento integral (100%) do critério de acessibilidade, que preconiza a disponibilidade dos dados via web sem barreiras de acesso. A existência de uma API funcional, que permite o acesso programático e automatizado, corrobora o atendimento pleno aos requisitos para a pontuação máxima. | G5: =D5*E5 -> 5
A6: Dados Abertos | B6: D5 | C6: Dados processados por máquina | D6: 1 | E6: 5 | F6: Verifica-se que o conjunto de dados é disponibilizado em formato XLSX. Apesar de ser um formato estruturado, que permite um processamento básico por máquina, ele não atende às especificações técnicas do padrão ePing. Mesmo assim atribui-se o nível 5, pois, embora utilize um formato proprietário, o arquivo é estruturado e processável por máquina. | G6: =D6*E6 -> 5
A7: Dados Abertos | B7: D6 | C7: Acesso não discriminatório | D7: 1 | E7: 5 | F7: A verificação do conjunto de dados, por meio de seu portal web e da API, demonstrou que o acesso aos recursos é público e irrestrito. A análise confirmou a ausência de barreiras como a necessidade de cadastro, autenticação ou qualquer forma de registro prévio para o download dos arquivos. Esta condição atende integralmente ao critério estabelecido para a dimensão D6 (Acesso não discriminatório), que avalia a disponibilidade dos dados a todos os usuários sem distinção. Em conformidade com a métrica DGABr 2.0, que define o cumprimento de 100% do padrão como requisito para o nível máximo, atribui-se o Nível 5 a esta dimensão. | G7: =D7*E7 -> 5
A8: Dados Abertos | B8: D7 | C8: Dados não proprietários | D8: 1 | E8: 2 | F8: A análise do conjunto de dados revela uma inconsistência entre os formatos de arquivo declarados nos metadados e o recurso efetivamente disponibilizado. Embora o portal de dados e a API informem a existência de arquivos nos formatos não proprietários CSV e JSON, a verificação empírica demonstrou que todos os links de acesso direcionam para um único arquivo no formato XLSX, que é classificado como proprietário. Conforme a estrutura da métrica DGABr, a existência de uma recomendação ou padrão definido pela instituição que não é seguido na publicação dos dados caracteriza o Nível 2. Uma vez que a instituição declara a intenção de publicar em formatos abertos mas, na prática, disponibiliza apenas um formato proprietário, o cumprimento da dimensão é nulo. Desta forma, atribui-se o Nível 2 a esta dimensão, pois a norma estabelecida nos metadatos não foi executada. | G8: =D8*E8 -> 2
A9: Dados Abertos | B9: D8 | C9: Dados livres de licença | D9: 1 | E9: 2 | F9: Observa-se que o conjunto de dados utiliza a designação "Outro (Aberta)" no campo de licença. Esta classificação é genérica e não corresponde a um modelo de licenciamento padronizado e reconhecido para dados abertos, como as licenças Creative Commons (CC) ou a Open Data Commons Open Database License (ODbL), que são referenciadas pela métrica. A ausência de um instrumento legal específico impede a definição inequívoca dos termos de uso, modificação e redistribuição, não assegurando a conformidade com os princípios de licenciamento que garantem o reúso com restrições mínimas ou nulas. Diante da evidência, atribui-se o Nível 2 a esta dimensão. A justificativa fundamenta-se no critério da métrica DGABr, segundo o qual este nível se aplica quando uma recomendação existe, neste caso, o uso de licenças abertas padrão, mas a publicação dos dados não segue o que foi definido. A utilização de uma licença não especificada, ainda que nomeada como "aberta", representa uma falha na execução da prática recomendada, comprometendo a segurança jurídica necessária para o reúso efetivo dos dados. | G9: =D9*E9 -> 2
A10: Dados Abertos | B10: D9 | C10: URIs desenhadas | D10: 1 | E10: 2 | F10: A análise das URLs dos recursos associados ao conjunto de dados evidencia a adoção de uma estrutura de nomenclatura padronizada. Existe o uso de identificadores únicos (UUIDs) para o conjunto de dados e para o recurso específico, o que contribui para a estabilidade e persistência do endereço eletrônico. Contudo, a estrutura não é considerada "amigável" ou de fácil memorização, conforme preconizado pela métrica, pois é composta por códigos alfanuméricos extensos. A identificação semântica do conteúdo depende exclusivamente do nome do arquivo ao final da URL, e não de um padrão hierárquico legível em seu caminho. Para a atribuição de um nível em conformidade com a DGABr 2.0, contudo, exige-se, para os níveis 3, 4 e 5, a comprovação de uma "política de gestão e preservação de documentos arquivísticos digitais". Adicionalmente, a análise não registra a verificação da estabilidade e persistência dos links, um componente implícito na avaliação original. Sem a evidência documental da política de preservação e um teste de estabilidade, a atribuição de um nível superior a 2 não pode ser tecnicamente fundamentada. Por isso se atribui o Nível 2. Exemplo de URL do conjunto de dados: "http://dadosabertos.ifmg.edu.br/dataset/8bda23f1-4d6a-4732-80f1-950e5edfa902/resource/9e4553a0-ffe0-4a15-9cb7-cd6881c91b95/download/relacao-dos-cursos-de-pos-graduacao-lato-sensu.xlsx" | G10: =D10*E10 -> 2
A11: Dados Abertos | B11: D10 | C11: Dados ligados | D11: 1 | E11: 0 | F11: A análise do conjunto de dados indica a ausência de vínculos com fontes de dados externas que permitam a contextualização das informações, conforme preconizado pelo princípio de dados ligados (linked data). Não foram identificadas referências, como o uso de RDF (Resource Description Framework) ou outras tecnologias semânticas, que conectem os registros a outros vocabulários ou conjuntos de dados. De acordo com a estrutura da métrica DGABr, a não implementação do item avaliado na dimensão D10 justifica a atribuição do Nível 0. | G11: =D11*E11 -> 0
A12: Legal | B12: D11 | C12: Tipo de informação | D12: 3 | E12: 5 | F12: A dimensão D11 da métrica DGABr analisa se a informação disponibilizada possui respaldo na legislação e nos instrumentos normativos que regulam sua publicação. No caso dos dados referentes aos "Cursos de Pós-Graduação Lato Sensu do IFMG", trata-se de informação prevista na legislação brasileira, em especial nos artigos 7º e 8º da Lei de Acesso à Informação, que determinam a divulgação ativa desse tipo de dado. Dessa forma, o conjunto atende plenamente ao requisito estabelecido, alcançando o nível 5 na dimensão. | G12: =D12*E12 -> 15
A13: Legal | B13: D12 | C13: Gestão de dados sensíveis | D13: 3 | E13: 4 | F13: A análise do conjunto de dados indica a ausência de informações de natureza sensível ou pessoal. Conforme a especificação da dimensão D12 da métrica DGABr, a não aplicabilidade do tratamento de dados sensíveis a um conjunto de dados implica a atribuição do nível 4, uma vez que não há requisitos de dessensibilização ou gestão de sigilo a serem cumpridos. A avaliação, portanto, baseia-se na constatação de que o objeto avaliado não contém elementos que demandem tratamento específico de sensibilidade porém, registra-se a ausência de documentação explícita que detalhe a política de segurança ou os critérios utilizados pela instituição para classificar a sensibilidade dos dados, embora tal lacuna não impacte a pontuação desta dimensão no caso em análise. | G13: =D13*E13 -> 12
... A29: Reúso | B29: D28 | C29: Informações sobre o reúso de DGA | D29: 3 | E29: 0 | F29: A avaliação da dimensão D28 (Informações sobre o reúso) é intrinsecamente dependente da prévia identificação de produtos ou serviços que utilizem o conjunto de dados em análise, conforme estipulado pela dimensão D25. Uma consulta aos mecanismos de registro de reúso, como o Portal Brasileiro de Dados Abertos, não evidenciou a existência de aplicações, produtos ou serviços derivados do referido conjunto de dados. Diante da ausência do objeto de análise, um produto derivado do reúso dos dados, torna-se inviável verificar se este informa adequadamente a fonte dos DGA utilizados. Por conseguinte, atribui-se o Nível 0, em conformidade com a definição da métrica DGABr para situações em que o item avaliado não se aplica ou não existe. | G29: =D29*E29 -> 0
A30: Total de Pontos | G30: =SUM(G2:G29) -> 127
A31: Indicador de reúso | G31: =IF(G30<54,1,IF(G30<108,2,IF(G30<162,3,IF(G30<216,4,5)))) -> 3
A32: URL Portal próprio | D32: https://dadosabertos.ifmg.edu.br/dataset/pos_graduacao_lato_sensu
A33: URL Portal Brasileiro de Dados Abertos | D33: https://dados.gov.br/dados/conjuntos-dados/pos_graduacao_lato_sensu
A34: URL API | D34: https://dadosabertos.ifmg.edu.br/api/action/package_show?id=pos_graduacao_lato_sensu

Sheet cursos_mestrado_2024
A1: Perspectiva | B1: ID | C1: Dimensão | D1: Peso | E1: Nível (0-5) | F1: Itens Observados | G1: Total
A2: Dados Abertos | B2: D1 | C2: Dados completos | D2: 1 | E2: 1 | F2: O conjunto de dados "Cursos de mestrado do IFMG" disponibiliza informações referentes exclusivamente ao ano de 2024. A dimensão D1 (Dados completos) da métrica DGABr avalia a completude do conjunto, com ênfase na disponibilização de séries históricas integrais. A evidência observada, que consiste em dados de um único ano, indica uma publicação parcial, uma vez que não abrange o ano de 2025. Embora o PDA do IFMG preveja uma frequência de atualização anual, o que se relaciona à dimensão D3 (Dados atualizados). Além disso os dados possuem somente dois campos: Campus e Mestrado, o que o caracteriza como imcompleto, outros dados poderiam estar presentes no conjunto de dados. A métrica DGABr estabelece o Nível 1 para o cumprimento o caso em que o orgão somente publica os dados e não possui critérios para avaliar se os mesmos são completos. | G2: =E2*D2 -> 1
A3: Dados Abertos | B3: D2 | C3: Dados primários | D3: 1 | E3: 5 | F3: Constata-se que o conjunto de dados é composto por dados primários, visto que sua geração é atribuída à instituição responsável pelo registro das informações, sem evidências de tratamento interpretativo ou agregação. Dessa forma, o atendimento integral aos critérios da dimensão D2, que avalia a ausência de agregações e a proveniência direta da fonte, fundamenta a atribuição do Nível 5. | G3: =E3*D3 -> 5
A4: Dados Abertos | B4: D3 | C4: Dados atualizados / DGA atualizado | D4: 1 | E4: 5 | F4: A avaliação da dimensão D3 teve como base o PDA do IFMG e o conjunto de dados “Cursos de Mestrado do IFMG”. O plano define frequência anual de atualização para esse conjunto, o que se mostra compatível com a dinâmica de oferta dos cursos, também anual. Essa correspondência indica que as informações disponibilizadas estão atualizadas de forma adequada, permitindo atribuir o nível 5 para a dimensão. | G4: =E4*D4 -> 5
A5: Dados Abertos | B5: D4 | C5: Dados acessíveis | D5: 1 | E5: 5 | F5: Constatou-se que o conjunto de dados cumpre integralmente os requisitos da dimensão D4. A verificação empírica confirmou a acessibilidade pública dos recursos via interface web e por meio de uma API, sem a exigência de cadastro, autenticação ou qualquer outra forma de identificação para a recuperação dos dados. A disponibilidade de 100% dos dados por múltiplos canais de acesso direto e irrestrito fundamenta a atribuição do Nível 5, em conformidade com os critérios da métrica DGABr para resultados avançados. | G5: =E5*D5 -> 5
A6: Dados Abertos | B6: D5 | C6: Dados processados por máquina | D6: 1 | E6: 5 | F6: Verifica-se que o conjunto de dados é disponibilizado em formato XLSX. Apesar de ser um formato estruturado, que permite um processamento básico por máquina, ele não atende às especificações técnicas do padrão ePing. Mesmo assim atribui-se o nível 5, pois, embora utilize um formato proprietário, o arquivo é estruturado e processável por máquina. | G6: =E6*D6 -> 5
A7: Dados Abertos | B7: D6 | C7: Acesso não discriminatório | D7: 1 | E7: 5 | F7: O acesso ao conjunto de dados ocorre de forma pública e irrestrita, sendo disponibilizado tanto por meio de sua página web quanto via API. A verificação dos pontos de acesso indicados confirma a ausência de barreiras, como a exigência de cadastro, login ou qualquer outra forma de identificação para o download dos recursos. Esta conformidade integral com o princípio avaliado na dimensão D6 fundamenta a atribuição do Nível 5, uma vez que o requisito de acesso não discriminatório é cumprido em sua totalidade, conforme os critérios da métrica DGABr. | G7: =E7*D7 -> 5
A8: Dados Abertos | B8: D7 | C8: Dados não proprietários | D8: 1 | E8: 2 | F8: A análise do conjunto de dados revela uma inconsistência entre os formatos de arquivo declarados nos metadados e o recurso efetivamente disponibilizado. Embora o portal de dados e a API informem a existência de arquivos nos formatos não proprietários CSV e JSON, a verificação empírica demonstrou que todos os links de acesso direcionam para um único arquivo no formato XLSX, que é classificado como proprietário. Conforme a estrutura da métrica DGABr, a existência de uma recomendação ou padrão definido pela instituição que não é seguido na publicação dos dados caracteriza o Nível 2. Uma vez que a instituição declara a intenção de publicar em formatos abertos mas, na prática, disponibiliza apenas um formato proprietário, o cumprimento da dimensão é nulo. Desta forma, atribui-se o Nível 2 a esta dimensão, pois a norma estabelecida nos metadatos não foi executada. | G8: =E8*D8 -> 2
A9: Dados Abertos | B9: D8 | C9: Dados livres de licença | D9: 1 | E9: 2 | F9: Observa-se que o conjunto de dados utiliza a designação "Outro (Aberta)" no campo de licença. Esta classificação é genérica e não corresponde a um modelo de licenciamento padronizado e reconhecido para dados abertos, como as licenças Creative Commons (CC) ou a Open Data Commons Open Database License (ODbL), que são referenciadas pela métrica. A ausência de um instrumento legal específico impede a definição inequívoca dos termos de uso, modificação e redistribuição, não assegurando a conformidade com os princípios de licenciamento que garantem o reúso com restrições mínimas ou nulas. Diante da evidência, atribui-se o Nível 2 a esta dimensão. A justificativa fundamenta-se no critério da métrica DGABr, segundo o qual este nível se aplica quando uma recomendação existe, neste caso, o uso de licenças abertas padrão, mas a publicação dos dados não segue o que foi definido. A utilização de uma licença não especificada, ainda que nomeada como "aberta", representa uma falha na execução da prática recomendada, comprometendo a segurança jurídica necessária para o reúso efetivo dos dados. | G9: =E9*D9 -> 2
A10: Dados Abertos | B10: D9 | C10: URIs desenhadas | D10: 1 | E10: 2 | F10: A análise das URLs dos recursos associados ao conjunto de dados evidencia a adoção de uma estrutura de nomenclatura padronizada. Existe o uso de identificadores únicos (UUIDs) para o conjunto de dados e para o recurso específico, o que contribui para a estabilidade e persistência do endereço eletrônico. Contudo, a estrutura não é considerada "amigável" ou de fácil memorização, conforme preconizado pela métrica, pois é composta por códigos alfanuméricos extensos. A identificação semântica do conteúdo depende exclusivamente do nome do arquivo ao final da URL, e não de um padrão hierárquico legível em seu caminho. Para a atribuição de um nível em conformidade com a DGABr 2.0, contudo, exige-se, para os níveis 3, 4 e 5, a comprovação de uma "política de gestão e preservação de documentos arquivísticos digitais". Adicionalmente, a análise não registra a verificação da estabilidade e persistência dos links, um componente implícito na avaliação original. Sem a evidência documental da política de preservação e um teste de estabilidade, a atribuição de um nível superior a 2 não pode ser tecnicamente fundamentada. Por isso se atribui o Nível 2. Exemplo de URL do conjunto de dados: "http://dadosabertos.ifmg.edu.br/dataset/a23360a5-b7d3-4fe2-b12c-c1f14071a7ac/resource/88586558-a0ce-414d-aae2-def7913b7b77/download/cursos-de-mestrado-do-ifmg.xlsx" | G10: =E10*D10 -> 2
A11: Dados Abertos | B11: D10 | C11: Dados ligados | D11: 1 | E11: 0 | F11: A análise do conjunto de dados indica a ausência de vínculos com fontes de dados externas que permitam a contextualização das informações, conforme preconizado pelo princípio de dados ligados (linked data). Não foram identificadas referências, como o uso de RDF (Resource Description Framework) ou outras tecnologias semânticas, que conectem os registros a outros vocabulários ou conjuntos de dados. De acordo com a estrutura da métrica DGABr, a não implementação do item avaliado na dimensão D10 justifica a atribuição do Nível 0. | G11: =E11*D11 -> 0
A12: Legal | B12: D11 | C12: Tipo de informação | D12: 3 | E12: 5 | F12: A dimensão D11 da métrica DGABr analisa se a informação disponibilizada possui respaldo na legislação e nos instrumentos normativos que regulam sua publicação. No caso dos dados referentes aos "Cursos de mestrado do IFMG", trata-se de informação prevista na legislação brasileira, em especial nos artigos 7º e 8º da Lei de Acesso à Informação, que determinam a divulgação ativa desse tipo de dado. Dessa forma, o conjunto atende plenamente ao requisito estabelecido, alcançando o nível 5 na dimensão. | G12: =E12*D12 -> 15
A13: Legal | B13: D12 | C13: Gestão de dados sensíveis | D13: 3 | E13: 4 | F13: A análise do conjunto de dados indica a ausência de informações de natureza sensível ou pessoal. Conforme a especificação da dimensão D12 da métrica DGABr, a não aplicabilidade do tratamento de dados sensíveis a um conjunto de dados implica a atribuição do nível 4, uma vez que não há requisitos de dessensibilização ou gestão de sigilo a serem cumpridos. A avaliação, portanto, baseia-se na constatação de que o objeto avaliado não contém elementos que demandem tratamento específico de sensibilidade porém, registra-se a ausência de documentação explícita que detalhe a política de segurança ou os critérios utilizados pela instituição para classificar a sensibilidade dos dados, embora tal lacuna não impacte a pontuação desta dimensão no caso em análise. | G13: =E13*D13 -> 12
... A29: Reúso | B29: D28 | C29: Informações sobre o reúso de DGA | D29: 3 | E29: 0 | F29: A verificação no Portal Brasileiro de Dados Abertos, conforme a metodologia prevista na DGABr 2.0, não identificou o registro de aplicações, produtos ou serviços que reutilizem o conjunto de dados em análise. A dimensão D28 avalia se os produtos gerados a partir dos DGA informam explicitamente aos seus usuários a fonte dos dados e a frequência de sua atualização. Visto que a existência de tais produtos é um pré-requisito para esta avaliação, a ausência de evidências de reúso impede a análise do critério. Diante da inexistência de um objeto de avaliação, atribui-se o Nível 0 a esta dimensão, em conformidade com a estrutura da métrica. | G29: =E29*D29 -> 0
A30: Total de Pontos | G30: =SUM(G2:G29) -> 128
A31: Indicador de reúso | G31: =IF(G30<54,1,IF(G30<108,2,IF(G30<162,3,IF(G30<216,4,5)))) -> 3
A32: URL Portal próprio | D32: https://dadosabertos.ifmg.edu.br/dataset/cursos_mestrado_2024
A33: URL Portal Brasileiro de Dados Abertos | D33: https://dados.gov.br/dados/conjuntos-dados/cursos_mestrado_2024
A34: URL API | D34: https://dadosabertos.ifmg.edu.br/api/action/package_show?id=cursos_mestrado_2024

Sheet candidatos-e-vagas-graducacao
A1: Perspectiva | B1: ID | C1: Dimensão | D1: Peso | E1: Nível (0-5) | F1: Itens Observados | G1: Total
A2: Dados Abertos | B2: D1 | C2: Dados completos | D2: 1 | E2: 0 | F2: A análise do conjunto de dados "Candidatos e Vagas nos Processos Seletivos de Cursos de Graduação" evidencia uma incompletude em duas frentes. Primeiramente, no aspecto temporal, observa-se a ausência de dados referentes ao primeiro semestre de 2025, em desacordo com a frequência de atualização semestral estabelecida no PDA da instituição. Em segundo lugar, a completude estrutural é comprometida pela apresentação de informações de forma agregada. A publicação de quantitativos consolidados, sem o detalhamento granular dos dados primários, inviabiliza o potencial de reúso informacional, um requisito central da métrica. Considerando a ausência de uma série histórica contínua e a falta de granularidade, o conjunto de dados não atende à definição de "dados completos". Com base nessas evidências, que indicam o não cumprimento dos critérios mínimos para a dimensão, atribui-se o Nível 0, conforme os parâmetros da métrica DGABr. | G2: =E2*D2 -> 0
A3: Dados Abertos | B3: D2 | C3: Dados primários | D3: 1 | E3: 0 | F3: A análise do conjunto de dados indica que, embora sejam gerados pela unidade organizacional responsável (Diretoria de Processos Seletivos), os dados são disponibilizados de forma agregada. A dimensão D2 (Dados primários) da métrica DGABr avalia a publicação de dados em seu nível máximo de granularidade, sem a aplicação de agregações ou modificações que alterem sua forma bruta. A constatação de que os dados são agregados contradiz diretamente o critério fundamental desta dimensão. Consequentemente, atribui-se o Nível 0, em conformidade com a definição da métrica para conjuntos de dados que não cumprem o requisito avaliado. A justificativa se alinha ao critério de que dados não primários, por definição, não atendem à dimensão, independentemente de sua integridade ou origem. | G3: =E3*D3 -> 0
A4: Dados Abertos | B4: D3 | C4: Dados atualizados / DGA atualizado | D4: 1 | E4: 5 | F4: A análise do conjunto de dados "Candidatos e Vagas nos Processos Seletivos de Cursos de Graduação" e do PDA do IFMG (vigência 2023-2025) fundamenta a avaliação. O referido PDA estabelece uma frequência de atualização semestral para este conjunto de dados. Como o IFMG oferece cursos de Graduação com dinámica de ingressos semestralmente essa atualização é condizente com nível 5. | G4: =E4*D4 -> 5
A5: Dados Abertos | B5: D4 | C5: Dados acessíveis | D5: 1 | E5: 5 | F5: Constatou-se que o conjunto de dados é acessível publicamente via web, não sendo exigido cadastro, login ou qualquer outra forma de identificação para o acesso. Adicionalmente, verificou-se a disponibilização de uma API, cuja funcionalidade para download dos dados foi confirmada. A evidência demonstra o cumprimento integral (100%) dos critérios estabelecidos para a dimensão D4 (Dados acessíveis), que avalia se os dados estão disponíveis sem barreiras de acesso. A ausência total de restrições, alinhada à disponibilização de múltiplos meios de acesso (direto e via API), fundamenta a atribuição do Nível 5. Esta classificação é consistente com a definição da métrica DGABr, que reserva o nível máximo para os casos em que 100% dos padrões e recomendações definidos para a dimensão são atendidos. | G5: =E5*D5 -> 5
A6: Dados Abertos | B6: D5 | C6: Dados processados por máquina | D6: 1 | E6: 4 | F6: Observou-se que o conjunto de dados é disponibilizado em formatos estruturados, o que atende ao critério fundamental da dimensão D5. A métrica DGABr 2.0, em sua revisão, especifica que os níveis superiores desta dimensão (3, 4 e 5) requerem conformidade com especificações técnicas do ePing. Durante a verificação dos arquivos, identificou-se uma inconformidade pontual: um dos recursos, cujo conteúdo corresponde ao formato CSV, foi nomeado com a extensão incorreta `.xlsx`. A referida falha, embora não comprometa a processabilidade do dado após a correção do nome do arquivo, ou até do uso do arquivo JSON, representa um desvio do padrão esperado e impede a atribuição do Nível 5, que exige 100% de conformidade. Contudo, por se tratar de uma ocorrência isolada que não afeta a totalidade dos recursos disponibilizados, considera-se que o critério de, no mínimo, 80% de adequação foi satisfeito. Desta forma, atribui-se o Nível 4, conforme a escala percentual definida pela métrica. | G6: =E6*D6 -> 4
A7: Dados Abertos | B7: D6 | C7: Acesso não discriminatório | D7: 1 | E7: 5 | F7: A análise do conjunto de dados evidenciou que o acesso aos recursos é público e irrestrito, sendo disponibilizado tanto por meio de sua página web quanto via API. A verificação dos pontos de acesso indicados confirmou a ausência de barreiras, como a exigência de cadastro, login ou qualquer outra forma de autenticação para o download dos dados. A completa aderência ao critério de acesso não discriminatório, observada em todos os canais de distribuição disponíveis, justifica a atribuição do Nível 5. De acordo com a estrutura da métrica DGABr, este nível é designado quando há cumprimento integral (100%) da dimensão avaliada. | G7: =E7*D7 -> 5
A8: Dados Abertos | B8: D7 | C8: Dados não proprietários | D8: 1 | E8: 4 | F8: Constatou-se que os recursos do conjunto de dados são disponibilizados em formatos não proprietários. A verificação dos arquivos para download e da resposta da API indicou o uso exclusivo dos formatos CSV e JSON. Durante a verificação dos arquivos, identificou-se uma inconformidade pontual: um dos recursos, cujo conteúdo corresponde ao formato CSV, foi nomeado com a extensão incorreta `.xlsx`. Uma vez que a totalidade dos formatos oferecidos atende ao critério da dimensão D7, atribui-se o Nível 5, em conformidade com a exigência de 100% de cumprimento para esta classificação. A referida falha, embora não comprometa a processabilidade do dado após a correção do nome do arquivo, ou até do uso do arquivo JSON, representa um desvio do padrão esperado e impede a atribuição do Nível 5, que exige 100% de conformidade. Contudo, por se tratar de uma ocorrência isolada que não afeta a totalidade dos recursos disponibilizados, considera-se que o critério de, no mínimo, 80% de adequação foi satisfeito. Desta forma, atribui-se o Nível 4, conforme a escala percentual definida pela métrica. | G8: =E8*D8 -> 4
A9: Dados Abertos | B9: D8 | C9: Dados livres de licença | D9: 1 | E9: 2 | F9: Observa-se que o conjunto de dados utiliza a designação "Outro (Aberta)" no campo de licença. Esta classificação é genérica e não corresponde a um modelo de licenciamento padronizado e reconhecido para dados abertos, como as licenças Creative Commons (CC) ou a Open Data Commons Open Database License (ODbL), que são referenciadas pela métrica. A ausência de um instrumento legal específico impede a definição inequívoca dos termos de uso, modificação e redistribuição, não assegurando a conformidade com os princípios de licenciamento que garantem o reúso com restrições mínimas ou nulas. Diante da evidência, atribui-se o Nível 2 a esta dimensão. A justificativa fundamenta-se no critério da métrica DGABr, segundo o qual este nível se aplica quando uma recomendação existe, neste caso, o uso de licenças abertas padrão, mas a publicação dos dados não segue o que foi definido. A utilização de uma licença não especificada, ainda que nomeada como "aberta", representa uma falha na execução da prática recomendada, comprometendo a segurança jurídica necessária para o reúso efetivo dos dados. | G9: =E9*D9 -> 2
A10: Dados Abertos | B10: D9 | C10: URIs desenhadas | D10: 1 | E10: 2 | F10: A análise das URLs dos recursos associados ao conjunto de dados evidencia a adoção de uma estrutura de nomenclatura padronizada. Existe o uso de identificadores únicos (UUIDs) para o conjunto de dados e para o recurso específico, o que contribui para a estabilidade e persistência do endereço eletrônico. Contudo, a estrutura não é considerada "amigável" ou de fácil memorização, conforme preconizado pela métrica, pois é composta por códigos alfanuméricos extensos. A identificação semântica do conteúdo depende exclusivamente do nome do arquivo ao final da URL, e não de um padrão hierárquico legível em seu caminho. Para a atribuição de um nível em conformidade com a DGABr 2.0, contudo, exige-se, para os níveis 3, 4 e 5, a comprovação de uma "política de gestão e preservação de documentos arquivísticos digitais". Adicionalmente, a análise não registra a verificação da estabilidade e persistência dos links, um componente implícito na avaliação original. Sem a evidência documental da política de preservação e um teste de estabilidade, a atribuição de um nível superior a 2 não pode ser tecnicamente fundamentada. Por isso se atribui o Nível 2. Exemplo de URL do conjunto de dados: "http://dadosabertos.ifmg.edu.br/dataset/8e24ca57-6868-4f37-b268-0d297552bee9/resource/685d6664-20ee-44f0-bf01-555457f0718f/download/candidatos-e-vagas-cursos-de-graduacao-2024-2" | G10: =E10*D10 -> 2
A11: Dados Abertos | B11: D10 | C11: Dados ligados | D11: 1 | E11: 0 | F11: A análise do conjunto de dados indica a ausência de vínculos com fontes de dados externas que permitam a contextualização das informações, conforme preconizado pelo princípio de dados ligados (linked data). Não foram identificadas referências, como o uso de RDF (Resource Description Framework) ou outras tecnologias semânticas, que conectem os registros a outros vocabulários ou conjuntos de dados. De acordo com a estrutura da métrica DGABr, a não implementação do item avaliado na dimensão D10 justifica a atribuição do Nível 0. | G11: =E11*D11 -> 0
A12: Legal | B12: D11 | C12: Tipo de informação | D12: 3 | E12: 5 | F12: A dimensão D11 da métrica DGABr analisa se a informação disponibilizada possui respaldo na legislação e nos instrumentos normativos que regulam sua publicação. No caso dos dados referentes aos "Candidatos e Vagas nos Processos Seletivos de Cursos de Graduação", trata-se de informação prevista na legislação brasileira, em especial nos artigos 7º e 8º da Lei de Acesso à Informação, que determinam a divulgação ativa desse tipo de dado. Dessa forma, o conjunto atende plenamente ao requisito estabelecido, alcançando o nível 5 na dimensão. | G12: =E12*D12 -> 15
A13: Legal | B13: D12 | C13: Gestão de dados sensíveis | D13: 3 | E13: 4 | F13: A análise do conjunto de dados indica a ausência de informações de natureza sensível ou pessoal. Conforme a especificação da dimensão D12 da métrica DGABr, a não aplicabilidade do tratamento de dados sensíveis a um conjunto de dados implica a atribuição do nível 4, uma vez que não há requisitos de dessensibilização ou gestão de sigilo a serem cumpridos. A avaliação, portanto, baseia-se na constatação de que o objeto avaliado não contém elementos que demandem tratamento específico de sensibilidade porém, registra-se a ausência de documentação explícita que detalhe a política de segurança ou os critérios utilizados pela instituição para classificar a sensibilidade dos dados, embora tal lacuna não impacte a pontuação desta dimensão no caso em análise. | G13: =E13*D13 -> 12
... A29: Reúso | B29: D28 | C29: Informações sobre o reúso de DGA | D29: 3 | E29: 0 | F29: Não se identificou a existência de aplicações, produtos ou serviços que reutilizem o conjunto de dados em análise, conforme verificação nos registros de reúso do Portal Brasileiro de Dados Abertos. A ausência de aplicações que comprovem o reúso, avaliada na dimensão D25, constitui um impedimento técnico para a análise da dimensão D28, cujo objetivo é verificar se os produtos gerados informam sobre as fontes de DGA utilizadas. Visto que o pressuposto para a avaliação não foi satisfeito, atribui-se o Nível 0 a esta dimensão, em conformidade com a estrutura metodológica da métrica DGABr. | G29: =E29*D29 -> 0
A30: Total de Pontos | G30: =SUM(G2:G29) -> 133
A31: Indicador de reúso | G31: =IF(G30<54,1,IF(G30<108,2,IF(G30<162,3,IF(G30<216,4,5)))) -> 3
A32: URL Portal próprio | D32: https://dadosabertos.ifmg.edu.br/dataset/candidatos-e-vagas-nos-processos-seletivos-de-cursos-de-graduacao
A33: URL Portal Brasileiro de Dados Abertos | D33: https://dados.gov.br/dados/conjuntos-dados/candidatos-e-vagas-nos-processos-seletivos-de-cursos-de-graduacao
A34: URL API | D34: https://dadosabertos.ifmg.edu.br/api/action/package_show?id=candidatos-e-vagas-nos-processos-seletivos-de-cursos-de-graduacao

Sheet disciplinas-dos-cursos-de-grdua
A1: Perspectiva | B1: ID | C1: Dimensão | D1: Peso | E1: Nível (0-5) | F1: Itens Observados | G1: Total
A2: Dados Abertos | B2: D1 | C2: Dados completos | D2: 1 | E2: 0 | F2: A análise do conjunto de dados "Disciplinas dos Cursos de Graduação" indica que as informações publicadas se referem ao primeiro semestre letivo de 2024. A verificação do PDA mais recente para o período 2023-2025, contudo, revela que este conjunto de dados não consta entre os compromissos de publicação formalizados pela instituição. A ausência de previsão no PDA impede a aferição da completude dos dados, uma vez que não há um escopo definido (e.g., séries históricas, variáveis obrigatórias) contra o qual a publicação possa ser comparada. Diante da inexistência de uma definição institucional para o item avaliado, atribui-se o Nível 0 a esta dimensão. A classificação se fundamenta no critério da métrica DGABr que estabelece o Nível 0 para situações em que "não há definição para o item avaliado", ainda que o dado esteja publicado. A lacuna evidenciada não reside na publicação em si, mas na ausência de sua formalização e detalhamento no instrumento de planejamento de dados abertos. | G2: =E2*D2 -> 0
A3: Dados Abertos | B3: D2 | C3: Dados primários | D3: 1 | E3: 5 | F3: O conjunto de dados é gerado pela Coordenadoria de Registro Acadêmico, unidade institucional responsável pelo registro primário das informações de inscrições e oferta de vagas. A análise da estrutura e do conteúdo dos dados não revela a aplicação de agregações, modificações ou tratamentos interpretativos, indicando que os dados são disponibilizados em sua granularidade máxima. Tais características correspondem à definição de dados primários da métrica DGABr 2.0, o que fundamenta a atribuição do Nível 5, por representar o cumprimento integral do critério. | G3: =E3*D3 -> 5
A4: Dados Abertos | B4: D3 | C4: Dados atualizados / DGA atualizado | D4: 1 | E4: 0 | F4: Constata-se que o conjunto de dados "Disciplinas dos Cursos de Graduação" não se encontra inventariado no PDA. Esta ausência impede a aferição da sua conformidade temporal, pois não há um parâmetro de frequência de atualização formalmente estabelecido para este recurso específico, conforme preconiza a dimensão D3. Embora o conjunto contenha informações referentes ao primeiro semestre de 2024, a inexistência de um compromisso documentado no PDA caracteriza uma lacuna na definição do item avaliado. Diante da ausência de uma frequência de atualização definida no instrumento de planejamento, o que inviabiliza a verificação do cumprimento, atribui-se o Nível 0. A métrica DGABr, em sua dimensão D3, avalia a execução de uma periodicidade previamente declarada, requisito que não pode ser verificado neste caso, alinhando-se à justificativa de nível em que a instituição não possui definição para o item avaliado. | G4: =E4*D4 -> 0
A5: Dados Abertos | B5: D4 | C5: Dados acessíveis | D5: 1 | E5: 5 | F5: Verifica-se que o conjunto de dados cumpre os requisitos da dimensão D4 (Dados acessíveis), pois está disponível para acesso público via web sem a exigência de cadastro, login ou qualquer outra forma de identificação. A existência de uma API, conforme evidenciado no teste de acesso documentado, reforça a ausência de barreiras técnicas e permite a recuperação automatizada dos dados, o que é consistente com os princípios fundamentais de dados abertos. Com base nessas observações, atribui-se o Nível 5 a esta dimensão. A justificativa para tal nível reside no cumprimento integral (100%) do critério estabelecido pela métrica, que define o grau máximo de acessibilidade como a disponibilização dos dados de forma irrestrita e direta. | G5: =E5*D5 -> 5
A6: Dados Abertos | B6: D5 | C6: Dados processados por máquina | D6: 1 | E6: 5 | F6: A análise do conjunto de dados evidencia que os recursos são disponibilizados em formatos estruturados (CSV e JSON), bem como por meio de uma API, o que atende ao critério fundamental de processamento por máquina. Adicionalmente, a observada conformidade com as especificações técnicas do ePING cumpre o requisito introduzido na métrica DGABr 2.0 para os níveis de avaliação mais elevados. A combinação da oferta de múltiplos formatos estruturados, acesso via API e a aderência aos padrões de interoperabilidade governamentais fundamenta a atribuição de um nível de cumprimento integral para esta dimensão. | G6: =E6*D6 -> 5
A7: Dados Abertos | B7: D6 | C7: Acesso não discriminatório | D7: 1 | E7: 5 | F7: Constata-se que o conjunto de dados é disponibilizado para acesso público por meio de interface web e por uma API, conforme os endereços eletrônicos fornecidos como evidência. A verificação de ambos os pontos de acesso demonstra que o download dos recursos não requer cadastro, login ou qualquer outra forma de identificação prévia do usuário. O acesso irrestrito, tanto para consumo humano (via portal) quanto automatizado (via API), cumpre integralmente os critérios definidos para a dimensão D6. Portanto, atribui-se o Nível 5, em conformidade com a métrica DGABr, que estipula este nível para dados disponibilizados sem barreiras discriminatórias de acesso. | G7: =E7*D7 -> 5
A8: Dados Abertos | B8: D7 | C8: Dados não proprietários | D8: 1 | E8: 5 | F8: A análise do conjunto de dados evidencia que os arquivos são disponibilizados nos formatos CSV e JSON. A verificação dos recursos, acessados tanto por download direto quanto via API, confirma que ambos os formatos são classificados como não proprietários, atendendo aos critérios estabelecidos pela métrica DGABr para a dimensão D7. Visto que a totalidade (100%) dos formatos oferecidos cumpre o requisito, atribui-se o Nível 5, que corresponde à execução integral do padrão avaliado. | G8: =E8*D8 -> 5
A9: Dados Abertos | B9: D8 | C9: Dados livres de licença | D9: 1 | E9: 2 | F9: Observa-se que o conjunto de dados utiliza a designação "Outro (Aberta)" no campo de licença. Esta classificação é genérica e não corresponde a um modelo de licenciamento padronizado e reconhecido para dados abertos, como as licenças Creative Commons (CC) ou a Open Data Commons Open Database License (ODbL), que são referenciadas pela métrica. A ausência de um instrumento legal específico impede a definição inequívoca dos termos de uso, modificação e redistribuição, não assegurando a conformidade com os princípios de licenciamento que garantem o reúso com restrições mínimas ou nulas. Diante da evidência, atribui-se o Nível 2 a esta dimensão. A justificativa fundamenta-se no critério da métrica DGABr, segundo o qual este nível se aplica quando uma recomendação existe, neste caso, o uso de licenças abertas padrão, mas a publicação dos dados não segue o que foi definido. A utilização de uma licença não especificada, ainda que nomeada como "aberta", representa uma falha na execução da prática recomendada, comprometendo a segurança jurídica necessária para o reúso efetivo dos dados. | G9: =E9*D9 -> 2
A10: Dados Abertos | B10: D9 | C10: URIs desenhadas | D10: 1 | E10: 2 | F10: A análise das URLs dos recursos associados ao conjunto de dados evidencia a adoção de uma estrutura de nomenclatura padronizada. Existe o uso de identificadores únicos (UUIDs) para o conjunto de dados e para o recurso específico, o que contribui para a estabilidade e persistência do endereço eletrônico. Contudo, a estrutura não é considerada "amigável" ou de fácil memorização, conforme preconizado pela métrica, pois é composta por códigos alfanuméricos extensos. A identificação semântica do conteúdo depende exclusivamente do nome do arquivo ao final da URL, e não de um padrão hierárquico legível em seu caminho. Para a atribuição de um nível em conformidade com a DGABr 2.0, contudo, exige-se, para os níveis 3, 4 e 5, a comprovação de uma "política de gestão e preservação de documentos arquivísticos digitais". Adicionalmente, a análise não registra a verificação da estabilidade e persistência dos links, um componente implícito na avaliação original. Sem a evidência documental da política de preservação e um teste de estabilidade, a atribuição de um nível superior a 2 não pode ser tecnicamente fundamentada. Por isso se atribui o Nível 2. Exemplo de URL do conjunto de dados: "http://dadosabertos.ifmg.edu.br/dataset/82ba4ef8-1d20-4af5-862e-4ef3f8a24663/resource/1e501e0d-e5b1-4be8-8017-7911ce2233e7/download/conjunto-de-dados-disciplinas-dos-cursos-de-graduacao.csv" | G10: =E10*D10 -> 2
A11: Dados Abertos | B11: D10 | C11: Dados ligados | D11: 1 | E11: 0 | F11: A análise do conjunto de dados indica a ausência de vínculos com fontes de dados externas que permitam a contextualização das informações, conforme preconizado pelo princípio de dados ligados (linked data). Não foram identificadas referências, como o uso de RDF (Resource Description Framework) ou outras tecnologias semânticas, que conectem os registros a outros vocabulários ou conjuntos de dados. De acordo com a estrutura da métrica DGABr, a não implementação do item avaliado na dimensão D10 justifica a atribuição do Nível 0. | G11: =E11*D11 -> 0
A12: Legal | B12: D11 | C12: Tipo de informação | D12: 3 | E12: 5 | F12: A dimensão D11 da métrica DGABr analisa se a informação disponibilizada possui respaldo na legislação e nos instrumentos normativos que regulam sua publicação. No caso dos dados referentes aos "Disciplinas dos Cursos de Graduação", trata-se de informação prevista na legislação brasileira, em especial nos artigos 7º e 8º da Lei de Acesso à Informação, que determinam a divulgação ativa desse tipo de dado. Dessa forma, o conjunto atende plenamente ao requisito estabelecido, alcançando o nível 5 na dimensão. | G12: =E12*D12 -> 15
A13: Legal | B13: D12 | C13: Gestão de dados sensíveis | D13: 3 | E13: 4 | F13: A análise do conjunto de dados indica a ausência de informações de natureza sensível ou pessoal. Conforme a especificação da dimensão D12 da métrica DGABr, a não aplicabilidade do tratamento de dados sensíveis a um conjunto de dados implica a atribuição do nível 4, uma vez que não há requisitos de dessensibilização ou gestão de sigilo a serem cumpridos. A avaliação, portanto, baseia-se na constatação de que o objeto avaliado não contém elementos que demandem tratamento específico de sensibilidade porém, registra-se a ausência de documentação explícita que detalhe a política de segurança ou os critérios utilizados pela instituição para classificar a sensibilidade dos dados, embora tal lacuna não impacte a pontuação desta dimensão no caso em análise. | G13: =E13*D13 -> 12
... A29: Reúso | B29: D28 | C29: Informações sobre o reúso de DGA | D29: 3 | E29: 0 | F29: Não se identificou, por meio da consulta ao Portal Brasileiro de Dados Abertos ou outras fontes, a existência de produtos, serviços ou aplicações que reutilizem o conjunto de dados analisado. A dimensão D28 avalia se os produtos gerados a partir dos DGA informam explicitamente sobre as fontes de dados utilizadas e sua frequência de atualização. A ausência de evidências de reúso impede, por conseguinte, a verificação dos critérios estabelecidos para esta dimensão. Dessa forma, atribui-se o Nível 0, em conformidade com a estrutura da métrica DGABr, que designa este nível para situações em que o item avaliado não é encontrado ou aplicável. A justificativa fundamenta-se na falta de um objeto de análise , o produto derivado dos dados , para a avaliação da transparência de suas fontes. | G29: =E29*D29 -> 0
A30: Total de Pontos | G30: =SUM(G2:G29) -> 135
A31: Indicador de reúso | G31: =IF(G30<54,1,IF(G30<108,2,IF(G30<162,3,IF(G30<216,4,5)))) -> 3
A32: URL Portal próprio | D32: https://dadosabertos.ifmg.edu.br/dataset/disciplinas-dos-cursos-de-grduacao
A33: URL Portal Brasileiro de Dados Abertos | D33: https://dados.gov.br/dados/conjuntos-dados/disciplinas-dos-cursos-de-grduacao
A34: URL API | D34: https://dadosabertos.ifmg.edu.br/api/action/package_show?id=disciplinas-dos-cursos-de-grduacao

Sheet disciplinas-dos-cursos-tecnicos
A1: Perspectiva | B1: ID | C1: Dimensão | D1: Peso | E1: Nível (0-5) | F1: Itens Observados | G1: Total
A2: Dados Abertos | B2: D1 | C2: Dados completos | D2: 1 | E2: 0 | F2: A análise do conjunto de dados "Disciplinas dos Cursos Técnicos" indica que este abrange o primeiro semestre letivo de 2024. A verificação do PDA da instituição, com vigência para o período 2023-2025, revela que este conjunto de dados não consta entre os compromissos de publicação formalmente estabelecidos. A métrica DGABr, em sua dimensão D1, avalia a completude dos dados em relação a um escopo previamente definido, como séries históricas ou a totalidade das variáveis planejadas, que é tipicamente documentado no PDA. A ausência de tal definição no plano impede a aferição objetiva da completude do conjunto de dados publicado. Diante da inexistência de um parâmetro formal para a avaliação, atribui-se o Nível 0 a esta dimensão. A justificativa para esta classificação reside no fato de que, embora os dados estejam publicados, o critério de "completude", conforme previsto pela metodologia da métrica, não pode ser mensurado. Tal cenário caracteriza uma lacuna na definição do escopo do item avaliado, alinhando-se à descrição do Nível 0, que se aplica quando "não tem definição para o item avaliado". | G2: =E2*D2 -> 0
A3: Dados Abertos | B3: D2 | C3: Dados primários | D3: 1 | E3: 5 | F3: A análise do conjunto de dados indica que sua origem é a Coordenadoria de Registro Acadêmico, unidade institucionalmente responsável pelo registro das informações. Esta proveniência corrobora a natureza primária dos dados, conforme definido pela métrica, que preconiza a coleta direta na fonte, com máxima granularidade e sem modificações. Não foram identificados indícios de tratamento interpretativo ou processos de agregação sobre os dados brutos disponibilizados. Com base nessas evidências, atribui-se o Nível 5, correspondente ao cumprimento integral (100%) do critério para esta dimensão. | G3: =E3*D3 -> 5
A4: Dados Abertos | B4: D3 | C4: Dados atualizados / DGA atualizado | D4: 1 | E4: 0 | F4: A análise do PDA(2023/08-2025/08) demonstra que o conjunto de dados "Disciplinas dos Cursos Técnicos" não está listado entre os compromissos de publicação formalmente estabelecidos pela instituição. A ausência deste conjunto de dados no PDA implica a inexistência de uma frequência de atualização definida, que serviria como parâmetro para a avaliação desta dimensão. A métrica DGABr, em sua dimensão D3, avalia especificamente o cumprimento da periodicidade de atualização previamente definida pelo órgão. Uma vez que não há um compromisso formal que estabeleça tal periodicidade, a aferição do seu cumprimento é inviabilizada. De acordo com os critérios da métrica, o Nível 0 é atribuído quando "não tem definição para o item avaliado". Portanto, atribui-se o Nível 0 a esta dimensão. | G4: =E4*D4 -> 0
A5: Dados Abertos | B5: D4 | C5: Dados acessíveis | D5: 1 | E5: 5 | F5: Constata-se que o conjunto de dados cumpre integralmente os requisitos da dimensão D4 (Dados acessíveis). A análise evidencia que o acesso aos dados é público e realizado via web, sem a exigência de mecanismos de identificação, como cadastro ou login. Adicionalmente, a acessibilidade é reforçada pela disponibilização de uma API, cuja funcionalidade para download foi verificada por meio do acesso ao endereço `https://dadosabertos.ifmg.edu.br/api/action/package_show?id=disciplinas-dos-cursos-tecnicos`. A ausência total de barreiras de acesso, alinhada à oferta de múltiplos meios de obtenção dos dados (download direto e via API), demonstra 100% de conformidade com os critérios definidos pela métrica para esta dimensão. Diante do exposto, atribui-se o Nível 5. | G5: =E5*D5 -> 5
A6: Dados Abertos | B6: D5 | C6: Dados processados por máquina | D6: 1 | E6: 5 | F6: Constata-se que o conjunto de dados é disponibilizado em formatos estruturados (CSV e JSON), os quais são processáveis por máquina. A análise indica que os formatos adotados estão em conformidade com as especificações técnicas do ePing. Este achado atende integralmente aos critérios da dimensão D5 na métrica DGABr 2.0, que para os níveis avançados requer não apenas a estruturação dos dados, mas também a aderência a padrões de interoperabilidade governamentais. Dessa forma, atribui-se o Nível 5, correspondente ao cumprimento de 100% do padrão definido. | G6: =E6*D6 -> 5
A7: Dados Abertos | B7: D6 | C7: Acesso não discriminatório | D7: 1 | E7: 5 | F7: A análise do conjunto de dados demonstrou que o acesso é público e irrestrito, realizado via web sem a necessidade de login, registro ou qualquer outra forma de identificação. A ausência de barreiras foi corroborada pela verificação do acesso por meio da API, que permitiu o download dos dados de forma automatizada. Tais evidências indicam o cumprimento integral (100%) dos critérios para a dimensão D6, o que fundamenta a atribuição do Nível 5. | G7: =E7*D7 -> 5
A8: Dados Abertos | B8: D7 | C8: Dados não proprietários | D8: 1 | E8: 5 | F8: Atribui-se o Nível 5 à dimensão D7. A justificativa fundamenta-se na evidência de que o conjunto de dados é integralmente disponibilizado em formatos não proprietários, especificamente CSV e JSON. A utilização exclusiva desses formatos atende a 100% do critério estabelecido pela métrica DGABr, que preconiza o uso de padrões abertos para garantir o acesso e o reúso da informação sem a necessidade de software específico. | G8: =E8*D8 -> 5
A9: Dados Abertos | B9: D8 | C9: Dados livres de licença | D9: 1 | E9: 2 | F9: Observa-se que o conjunto de dados utiliza a designação "Outro (Aberta)" no campo de licença. Esta classificação é genérica e não corresponde a um modelo de licenciamento padronizado e reconhecido para dados abertos, como as licenças Creative Commons (CC) ou a Open Data Commons Open Database License (ODbL), que são referenciadas pela métrica. A ausência de um instrumento legal específico impede a definição inequívoca dos termos de uso, modificação e redistribuição, não assegurando a conformidade com os princípios de licenciamento que garantem o reúso com restrições mínimas ou nulas. Diante da evidência, atribui-se o Nível 2 a esta dimensão. A justificativa fundamenta-se no critério da métrica DGABr, segundo o qual este nível se aplica quando uma recomendação existe, neste caso, o uso de licenças abertas padrão, mas a publicação dos dados não segue o que foi definido. A utilização de uma licença não especificada, ainda que nomeada como "aberta", representa uma falha na execução da prática recomendada, comprometendo a segurança jurídica necessária para o reúso efetivo dos dados. | G9: =E9*D9 -> 2
A10: Dados Abertos | B10: D9 | C10: URIs desenhadas | D10: 1 | E10: 2 | F10: A análise das URLs dos recursos associados ao conjunto de dados evidencia a adoção de uma estrutura de nomenclatura padronizada. Existe o uso de identificadores únicos (UUIDs) para o conjunto de dados e para o recurso específico, o que contribui para a estabilidade e persistência do endereço eletrônico. Contudo, a estrutura não é considerada "amigável" ou de fácil memorização, conforme preconizado pela métrica, pois é composta por códigos alfanuméricos extensos. A identificação semântica do conteúdo depende exclusivamente do nome do arquivo ao final da URL, e não de um padrão hierárquico legível em seu caminho. Para a atribuição de um nível em conformidade com a DGABr 2.0, contudo, exige-se, para os níveis 3, 4 e 5, a comprovação de uma "política de gestão e preservação de documentos arquivísticos digitais". Adicionalmente, a análise não registra a verificação da estabilidade e persistência dos links, um componente implícito na avaliação original. Sem a evidência documental da política de preservação e um teste de estabilidade, a atribuição de um nível superior a 2 não pode ser tecnicamente fundamentada. Por isso se atribui o Nível 2. Exemplo de URL do conjunto de dados: "http://dadosabertos.ifmg.edu.br/dataset/136d7786-af6c-4f86-b7e1-060cbda76630/resource/b8e24d31-7c58-4283-9676-de881cffd68d/download/conjunto-de-dados-disciplinas-dos-cursos-tecnicos.csv" | G10: =E10*D10 -> 2
A11: Dados Abertos | B11: D10 | C11: Dados ligados | D11: 1 | E11: 0 | F11: A análise do conjunto de dados indica a ausência de vínculos com fontes de dados externas que permitam a contextualização das informações, conforme preconizado pelo princípio de dados ligados (linked data). Não foram identificadas referências, como o uso de RDF (Resource Description Framework) ou outras tecnologias semânticas, que conectem os registros a outros vocabulários ou conjuntos de dados. De acordo com a estrutura da métrica DGABr, a não implementação do item avaliado na dimensão D10 justifica a atribuição do Nível 0. | G11: =E11*D11 -> 0
A12: Legal | B12: D11 | C12: Tipo de informação | D12: 3 | E12: 5 | F12: A dimensão D11 da métrica DGABr analisa se a informação disponibilizada possui respaldo na legislação e nos instrumentos normativos que regulam sua publicação. No caso dos dados referentes aos "Disciplinas dos Cursos Técnicos", trata-se de informação prevista na legislação brasileira, em especial nos artigos 7º e 8º da Lei de Acesso à Informação, que determinam a divulgação ativa desse tipo de dado. Dessa forma, o conjunto atende plenamente ao requisito estabelecido, alcançando o nível 5 na dimensão. | G12: =E12*D12 -> 15
A13: Legal | B13: D12 | C13: Gestão de dados sensíveis | D13: 3 | E13: 4 | F13: A análise do conjunto de dados indica a ausência de informações de natureza sensível ou pessoal. Conforme a especificação da dimensão D12 da métrica DGABr, a não aplicabilidade do tratamento de dados sensíveis a um conjunto de dados implica a atribuição do nível 4, uma vez que não há requisitos de dessensibilização ou gestão de sigilo a serem cumpridos. A avaliação, portanto, baseia-se na constatação de que o objeto avaliado não contém elementos que demandem tratamento específico de sensibilidade porém, registra-se a ausência de documentação explícita que detalhe a política de segurança ou os critérios utilizados pela instituição para classificar a sensibilidade dos dados, embora tal lacuna não impacte a pontuação desta dimensão no caso em análise. | G13: =E13*D13 -> 12
... A29: Reúso | B29: D28 | C29: Informações sobre o reúso de DGA | D29: 3 | E29: 0 | F29: A avaliação da dimensão D28, referente à disponibilização de informações sobre o reúso nos produtos gerados, é condicionada à existência de aplicações que utilizem o conjunto de dados em análise. A verificação realizada no Portal Brasileiro de Dados Abertos, conforme a metodologia de evidência para a perspectiva de Reúso, não identificou registros de produtos, serviços ou outras aplicações que reutilizassem os DGA do PRONATEC. Em decorrência da ausência de instâncias de reúso, a análise do critério , verificar se os produtos informam sobre a fonte e a frequência de atualização dos dados , é inaplicável. Desta forma, atribui-se o Nível 0, uma vez que a condição fundamental para a avaliação da dimensão não foi satisfeita, em alinhamento com a definição da métrica para itens não encontrados ou não aplicáveis. | G29: =E29*D29 -> 0
A30: Total de Pontos | G30: =SUM(G2:G29) -> 135
A31: Indicador de reúso | G31: =IF(G30<54,1,IF(G30<108,2,IF(G30<162,3,IF(G30<216,4,5)))) -> 3
A32: URL Portal próprio | D32: https://dadosabertos.ifmg.edu.br/dataset/disciplinas-dos-cursos-tecnicos
A33: URL Portal Brasileiro de Dados Abertos | D33: https://dados.gov.br/dados/conjuntos-dados/disciplinas-dos-cursos-tecnicos1
A34: URL API | D34: https://dadosabertos.ifmg.edu.br/api/action/package_show?id=disciplinas-dos-cursos-tecnicos

Sheet link-internet
A1: Perspectiva | B1: ID | C1: Dimensão | D1: Peso | E1: Nível (0-5) | F1: Itens Observados | G1: Total
A2: Dados Abertos | B2: D1 | C2: Dados completos | D2: 1 | E2: 0 | F2: A análise do conjunto de dados "Link de internet" evidencia a publicação de informações referentes ao ano de 2024. A avaliação da dimensão D1 (Dados completos), conforme a métrica DGABr, pressupõe a comparação entre o conteúdo publicado e o escopo definido no PDA do órgão. A consulta ao PDA mais recente (2023/08-2025/08) indica que o referido conjunto de dados não está listado no planejamento de publicações. A ausência de uma definição formal sobre a abrangência e o escopo esperados para este conjunto de dados inviabiliza a mensuração de sua completude em termos percentuais. Desta forma, atribui-se o Nível 0, em conformidade com o critério da métrica que se aplica quando "não tem definição para o item avaliado". A lacuna evidencial reside na inexistência de um parâmetro oficial no PDA contra o qual a completude do conjunto de dados pudesse ser aferida. | G2: =E2*D2 -> 0
A3: Dados Abertos | B3: D2 | C3: Dados primários | D3: 1 | E3: 5 | F3: A análise do conjunto de dados indica que a informação foi gerada a partir do sistema disponível em https://viaipe.rnp.br/, sendo o próprio órgão a fonte produtora. Não foram identificadas evidências de agregações, modificações ou tratamentos interpretativos que alterem a granularidade original dos dados. A disponibilização da informação em sua forma bruta, conforme coletada na fonte, atende integralmente ao critério de "dados primários" definido pela métrica DGABr. Dessa forma, o conjunto de dados cumpre em 100% o padrão estabelecido para a dimensão. Em conformidade com a estrutura de avaliação da métrica, atribui-se o Nível 5, correspondente ao cumprimento integral do requisito avaliado. | G3: =E3*D3 -> 5
A4: Dados Abertos | B4: D3 | C4: Dados atualizados / DGA atualizado | D4: 1 | E4: 0 | F4: Observa-se que o conjunto de dados "Link de internet" não consta no PDA da instituição. A métrica DGABr, em sua dimensão D3 (Dados atualizados), avalia a conformidade da publicação com a frequência de atualização previamente definida, parâmetro este que é tipicamente estabelecido no PDA. A ausência do referido conjunto de dados no plano implica a inexistência de um compromisso formal de atualização, o que inviabiliza a verificação de sua temporalidade conforme os critérios da métrica. Diante da ausência de um parâmetro de avaliação documentado, atribui-se o Nível 0. Esta classificação se fundamenta na definição da métrica, que especifica este nível para situações em que a instituição "não tem definição para o item avaliado". A falta de uma frequência de atualização planejada e registrada para o conjunto de dados em questão corresponde diretamente a este critério, caracterizando uma lacuna de evidência que impede a avaliação nos níveis superiores. | G4: =E4*D4 -> 0
A5: Dados Abertos | B5: D4 | C5: Dados acessíveis | D5: 1 | E5: 5 | F5: A análise do conjunto de dados constatou a sua acessibilidade pública por meio da web, sem a exigência de cadastro, login ou qualquer outra forma de identificação. Adicionalmente, foi verificada a disponibilização de acesso programático via API, cuja funcionalidade foi confirmada no endereço eletrônico documentado, permitindo o download automatizado dos dados. A coexistência de acesso direto e programático, ambos irrestritos, demonstra o cumprimento integral dos requisitos da dimensão D4 (Dados acessíveis). Tal conformidade justifica a atribuição do Nível 5, que, segundo a métrica DGABr, corresponde à disponibilização de 100% dos dados sem barreiras de acesso, atendendo plenamente aos critérios de acesso não discriminatório e processabilidade por máquina. | G5: =E5*D5 -> 5
A6: Dados Abertos | B6: D5 | C6: Dados processados por máquina | D6: 1 | E6: 5 | F6: O conjunto de dados é disponibilizado em formatos estruturados (JSON e CSV), o que satisfaz o critério fundamental de ser processável por máquina. A análise dos arquivos confirma que os dados seguem uma estrutura lógica e consistente, permitindo o processamento automatizado por aplicações computacionais. Adicionalmente, a avaliação conforme a métrica DGABr 2.0 para a dimensão D5 exige a verificação de aderência a especificações técnicas do ePING. A estrutura e os formatos utilizados demonstram conformidade com os padrões de interoperabilidade estabelecidos. O cumprimento integral de ambos os critérios , disponibilização em formato estruturado e alinhamento aos padrões técnicos governamentais , fundamenta a atribuição do Nível 5 para esta dimensão. | G6: =E6*D6 -> 5
A7: Dados Abertos | B7: D6 | C7: Acesso não discriminatório | D7: 1 | E7: 5 | F7: A análise do conjunto de dados e de seus pontos de acesso indica que o critério de acesso não discriminatório (D6) é integralmente atendido. O recurso está disponível para consulta e download direto por meio de sua página no portal de dados, bem como de forma programática via API, sem a requisição de cadastro, login ou qualquer outra forma de identificação do usuário. A validação das URLs dos recursos confirmou a ausência de restrições de acesso. Tendo em vista o cumprimento integral do requisito, que corresponde a 100% de conformidade, atribui-se o Nível 5 a esta dimensão. Esta avaliação está alinhada à estrutura da métrica DGABr, que define o Nível 5 para os casos em que os padrões e recomendações são atendidos em sua totalidade. | G7: =E7*D7 -> 5
A8: Dados Abertos | B8: D7 | C8: Dados não proprietários | D8: 1 | E8: 5 | F8: Verifica-se que o conjunto de dados é disponibilizado nos formatos CSV e JSON. Ambos são classificados como não proprietários, atendendo aos critérios estabelecidos pela dimensão D7 da métrica DGABr. Uma vez que a totalidade dos arquivos disponibilizados cumpre este requisito, o atendimento é considerado integral (100%). Com base nesta evidência, atribui-se o Nível 5, que corresponde ao cumprimento completo dos padrões e recomendações definidos para a dimensão. | G8: =E8*D8 -> 5
A9: Dados Abertos | B9: D8 | C9: Dados livres de licença | D9: 1 | E9: 2 | F9: Observa-se que o conjunto de dados utiliza a designação "Outro (Aberta)" no campo de licença. Esta classificação é genérica e não corresponde a um modelo de licenciamento padronizado e reconhecido para dados abertos, como as licenças Creative Commons (CC) ou a Open Data Commons Open Database License (ODbL), que são referenciadas pela métrica. A ausência de um instrumento legal específico impede a definição inequívoca dos termos de uso, modificação e redistribuição, não assegurando a conformidade com os princípios de licenciamento que garantem o reúso com restrições mínimas ou nulas. Diante da evidência, atribui-se o Nível 2 a esta dimensão. A justificativa fundamenta-se no critério da métrica DGABr, segundo o qual este nível se aplica quando uma recomendação existe, neste caso, o uso de licenças abertas padrão, mas a publicação dos dados não segue o que foi definido. A utilização de uma licença não especificada, ainda que nomeada como "aberta", representa uma falha na execução da prática recomendada, comprometendo a segurança jurídica necessária para o reúso efetivo dos dados. | G9: =E9*D9 -> 2
A10: Dados Abertos | B10: D9 | C10: URIs desenhadas | D10: 1 | E10: 2 | F10: A análise das URLs dos recursos associados ao conjunto de dados evidencia a adoção de uma estrutura de nomenclatura padronizada. Existe o uso de identificadores únicos (UUIDs) para o conjunto de dados e para o recurso específico, o que contribui para a estabilidade e persistência do endereço eletrônico. Contudo, a estrutura não é considerada "amigável" ou de fácil memorização, conforme preconizado pela métrica, pois é composta por códigos alfanuméricos extensos. A identificação semântica do conteúdo depende exclusivamente do nome do arquivo ao final da URL, e não de um padrão hierárquico legível em seu caminho. Para a atribuição de um nível em conformidade com a DGABr 2.0, contudo, exige-se, para os níveis 3, 4 e 5, a comprovação de uma "política de gestão e preservação de documentos arquivísticos digitais". Adicionalmente, a análise não registra a verificação da estabilidade e persistência dos links, um componente implícito na avaliação original. Sem a evidência documental da política de preservação e um teste de estabilidade, a atribuição de um nível superior a 2 não pode ser tecnicamente fundamentada. Por isso se atribui o Nível 2. Exemplo de URL do conjunto de dados: "http://dadosabertos.ifmg.edu.br/dataset/73072b7a-f3a2-43ec-86db-54a47ed08198/resource/6d846cce-fd03-46d2-8a28-16680addc529/download/conjunto-de-dados-links-de-internet.json" | G10: =E10*D10 -> 2
A11: Dados Abertos | B11: D10 | C11: Dados ligados | D11: 1 | E11: 0 | F11: A análise do conjunto de dados indica a ausência de vínculos com fontes de dados externas que permitam a contextualização das informações, conforme preconizado pelo princípio de dados ligados (linked data). Não foram identificadas referências, como o uso de RDF (Resource Description Framework) ou outras tecnologias semânticas, que conectem os registros a outros vocabulários ou conjuntos de dados. De acordo com a estrutura da métrica DGABr, a não implementação do item avaliado na dimensão D10 justifica a atribuição do Nível 0. | G11: =E11*D11 -> 0
A12: Legal | B12: D11 | C12: Tipo de informação | D12: 3 | E12: 5 | F12: A dimensão D11 da métrica DGABr analisa se a informação disponibilizada possui respaldo na legislação e nos instrumentos normativos que regulam sua publicação. No caso dos dados referentes aos "Link de internet dos campi", trata-se de informação prevista na legislação brasileira, em especial nos artigos 7º e 8º da Lei de Acesso à Informação, que determinam a divulgação ativa desse tipo de dado. Dessa forma, o conjunto atende plenamente ao requisito estabelecido, alcançando o nível 5 na dimensão. | G12: =E12*D12 -> 15
A13: Legal | B13: D12 | C13: Gestão de dados sensíveis | D13: 3 | E13: 4 | F13: A análise do conjunto de dados indica a ausência de informações de natureza sensível ou pessoal. Conforme a especificação da dimensão D12 da métrica DGABr, a não aplicabilidade do tratamento de dados sensíveis a um conjunto de dados implica a atribuição do nível 4, uma vez que não há requisitos de dessensibilização ou gestão de sigilo a serem cumpridos. A avaliação, portanto, baseia-se na constatação de que o objeto avaliado não contém elementos que demandem tratamento específico de sensibilidade porém, registra-se a ausência de documentação explícita que detalhe a política de segurança ou os critérios utilizados pela instituição para classificar a sensibilidade dos dados, embora tal lacuna não impacte a pontuação desta dimensão no caso em análise. | G13: =E13*D13 -> 12
... A29: Reúso | B29: D28 | C29: Informações sobre o reúso de DGA | D29: 3 | E29: 0 | F29: A análise não identificou aplicações, produtos ou serviços que reutilizassem o conjunto de dados em questão. A dimensão D28 avalia se os produtos gerados a partir dos DGA informam adequadamente sobre as fontes de dados utilizadas e sua frequência de atualização. Visto que não foram localizadas instâncias de reúso, torna-se inviável a verificação dos critérios desta dimensão, que é dependente da existência prévia de uma aplicação, conforme avaliado na dimensão D25. Desta forma, atribui-se o Nível 0, em conformidade com a métrica DGABr, que pressupõe a existência de um produto para que a informação sobre seu reúso possa ser avaliada. A evidência para esta conclusão baseia-se na ausência de registros de reúso no Portal Brasileiro de Dados Abertos, conforme consulta à URL de referência do conjunto de dados, o que constitui a principal fonte de verificação para esta dimensão, especialmente no contexto da DGABr 2.0. | G29: =E29*D29 -> 0
A30: Total de Pontos | G30: =SUM(G2:G29) -> 137
A31: Indicador de reúso | G31: =IF(G30<54,1,IF(G30<108,2,IF(G30<162,3,IF(G30<216,4,5)))) -> 3
A32: URL Portal próprio | D32: https://dadosabertos.ifmg.edu.br/dataset/link-internet
A33: URL Portal Brasileiro de Dados Abertos | D33: https://dados.gov.br/dados/conjuntos-dados/link-internet
A34: URL API | D34: https://dadosabertos.ifmg.edu.br/api/action/package_show?id=link-internet

Sheet chamados-de-suporte
A1: Perspectiva | B1: ID | C1: Dimensão | D1: Peso | E1: Nível (0-5) | F1: Itens Observados | G1: Total
A2: Dados Abertos | B2: D1 | C2: Dados completos | D2: 1 | E2: 0 | F2: A análise do conjunto de dados "Chamados de suporte", com escopo temporal referente ao ano de 2024, evidencia uma lacuna documental. O referido conjunto não consta no rol de publicações previstas no PDA do órgão, instrumento que, segundo a metodologia da métrica, serve de referência para aferir a completude (D1) ao estabelecer os campos e a abrangência esperados para cada conjunto de dados. Na ausência de tal previsão, torna-se tecnicamente inviável a verificação do atendimento aos critérios de completude. Esta ausência de uma definição formal para o item avaliado no âmbito do planejamento institucional fundamenta a atribuição do Nível 0. A publicação de um conjunto de dados não previsto no PDA, embora possa representar uma iniciativa de transparência, impede a avaliação objetiva de sua completude conforme os parâmetros estruturados pela métrica DGABr. | G2: =E2*D2 -> 0
A3: Dados Abertos | B3: D2 | C3: Dados primários | D3: 1 | E3: 5 | F3: A análise do conjunto de dados indica que sua origem é o sistema SUAP, sendo gerado pelo próprio órgão. As informações são apresentadas em sua granularidade original, sem evidências de processamento interpretativo ou agregação, o que as caracteriza como dados primários, conforme a definição da dimensão D2 da métrica DGABr. O cumprimento integral deste critério, que corresponde à disponibilização dos dados brutos coletados diretamente na fonte, fundamenta a atribuição do Nível 5. | G3: =E3*D3 -> 5
A4: Dados Abertos | B4: D3 | C4: Dados atualizados / DGA atualizado | D4: 1 | E4: 0 | F4: O conjunto de dados "Chamados de suporte" não consta no PDA mais recente (2023/08-2025/08), o que impede a aferição de uma frequência de atualização formalmente estabelecida pela instituição. Embora o recurso contenha registros referentes ao ano de 2024, a métrica DGABr, em sua dimensão D3, avalia o cumprimento de uma periodicidade previamente definida, seja no PDA ou nos metadados do próprio conjunto de dados. A ausência de tal definição constitui uma lacuna de evidência para a avaliação do cumprimento. Diante da inexistência de um compromisso de atualização documentado para este conjunto de dados, atribui-se o Nível 0. A justificativa para esta classificação reside no fato de que, para a dimensão em análise, não há uma norma ou recomendação definida pela instituição que permita aferir sua execução. Tal cenário alinha-se à descrição do Nível 0, que contempla a ausência de definição para o item avaliado. | G4: =E4*D4 -> 0
A5: Dados Abertos | B5: D4 | C5: Dados acessíveis | D5: 1 | E5: 5 | F5: Constatou-se que o conjunto de dados é acessível publicamente via web, não sendo exigido registro, login ou qualquer outra forma de identificação para o seu acesso. Adicionalmente, foi verificada a disponibilização de uma API, que viabiliza o download automatizado dos dados. Tais características demonstram o cumprimento integral (100%) dos critérios definidos pela métrica DGABr para a dimensão D4, que avalia a acessibilidade irrestrita da informação. Desta forma, atribui-se o Nível 5. | G5: =E5*D5 -> 5
A6: Dados Abertos | B6: D5 | C6: Dados processados por máquina | D6: 1 | E6: 5 | F6: Observa-se que o conjunto de dados é disponibilizado em formatos estruturados (CSV e JSON), acessíveis tanto para download direto quanto via API. A análise da documentação e dos próprios recursos indica que os formatos adotados estão em conformidade com as especificações técnicas dos Padrões de Interoperabilidade do Governo Eletrônico (ePING). Conforme a métrica DGABr 2.0, a avaliação dos níveis superiores (3, 4 e 5) para a dimensão D5 exige não apenas a estruturação dos dados, mas também a aderência a uma especificação técnica do ePING. A disponibilização integral do conjunto de dados nestas condições atende a 100% dos critérios estabelecidos, o que fundamenta a atribuição do Nível 5. | G6: =E6*D6 -> 5
A7: Dados Abertos | B7: D6 | C7: Acesso não discriminatório | D7: 1 | E7: 5 | F7: A análise do conjunto de dados e de seus respectivos recursos, disponibilizados tanto via portal web quanto por meio de API, evidencia que o acesso é público e irrestrito. Constatou-se a ausência da requisição de cadastro, login ou qualquer outra forma de identificação para o download dos arquivos, o que demonstra o cumprimento integral (100%) dos requisitos desta dimensão. Desta forma, atribui-se o Nível 5, em conformidade com os critérios da métrica DGABr para acesso não discriminatório. | G7: =E7*D7 -> 5
A8: Dados Abertos | B8: D7 | C8: Dados não proprietários | D8: 1 | E8: 5 | F8: A análise do conjunto de dados, acessado por meio do portal e da API especificados, evidencia que os recursos são disponibilizados nos formatos CSV e JSON. Ambos os formatos são classificados como não proprietários, atendendo integralmente aos critérios estabelecidos pela dimensão D7 da métrica DGABr. A disponibilização de 100% dos dados em formatos abertos e não proprietários corresponde ao cumprimento total do requisito avaliado. Com base nesta evidência, atribui-se à dimensão o Nível 5, que denota a conformidade integral com os padrões definidos para o item. | G8: =E8*D8 -> 5
A9: Dados Abertos | B9: D8 | C9: Dados livres de licença | D9: 1 | E9: 2 | F9: Observa-se que o conjunto de dados utiliza a designação "Outro (Aberta)" no campo de licença. Esta classificação é genérica e não corresponde a um modelo de licenciamento padronizado e reconhecido para dados abertos, como as licenças Creative Commons (CC) ou a Open Data Commons Open Database License (ODbL), que são referenciadas pela métrica. A ausência de um instrumento legal específico impede a definição inequívoca dos termos de uso, modificação e redistribuição, não assegurando a conformidade com os princípios de licenciamento que garantem o reúso com restrições mínimas ou nulas. Diante da evidência, atribui-se o Nível 2 a esta dimensão. A justificativa fundamenta-se no critério da métrica DGABr, segundo o qual este nível se aplica quando uma recomendação existe, neste caso, o uso de licenças abertas padrão, mas a publicação dos dados não segue o que foi definido. A utilização de uma licença não especificada, ainda que nomeada como "aberta", representa uma falha na execução da prática recomendada, comprometendo a segurança jurídica necessária para o reúso efetivo dos dados. | G9: =E9*D9 -> 2
A10: Dados Abertos | B10: D9 | C10: URIs desenhadas | D10: 1 | E10: 2 | F10: A análise das URLs dos recursos associados ao conjunto de dados evidencia a adoção de uma estrutura de nomenclatura padronizada. Existe o uso de identificadores únicos (UUIDs) para o conjunto de dados e para o recurso específico, o que contribui para a estabilidade e persistência do endereço eletrônico. Contudo, a estrutura não é considerada "amigável" ou de fácil memorização, conforme preconizado pela métrica, pois é composta por códigos alfanuméricos extensos. A identificação semântica do conteúdo depende exclusivamente do nome do arquivo ao final da URL, e não de um padrão hierárquico legível em seu caminho. Para a atribuição de um nível em conformidade com a DGABr 2.0, contudo, exige-se, para os níveis 3, 4 e 5, a comprovação de uma "política de gestão e preservação de documentos arquivísticos digitais". Adicionalmente, a análise não registra a verificação da estabilidade e persistência dos links, um componente implícito na avaliação original. Sem a evidência documental da política de preservação e um teste de estabilidade, a atribuição de um nível superior a 2 não pode ser tecnicamente fundamentada. Por isso se atribui o Nível 2. Exemplo de URL do conjunto de dados: "http://dadosabertos.ifmg.edu.br/dataset/8339d8d9-deca-4de7-9070-aa5052975292/resource/a7efa452-03d9-435d-82f8-f7344516ad72/download/conjunto-de-dados-chamados-de-suporte.csv" | G10: =E10*D10 -> 2
A11: Dados Abertos | B11: D10 | C11: Dados ligados | D11: 1 | E11: 0 | F11: A análise do conjunto de dados indica a ausência de vínculos com fontes de dados externas que permitam a contextualização das informações, conforme preconizado pelo princípio de dados ligados (linked data). Não foram identificadas referências, como o uso de RDF (Resource Description Framework) ou outras tecnologias semânticas, que conectem os registros a outros vocabulários ou conjuntos de dados. De acordo com a estrutura da métrica DGABr, a não implementação do item avaliado na dimensão D10 justifica a atribuição do Nível 0. | G11: =E11*D11 -> 0
A12: Legal | B12: D11 | C12: Tipo de informação | D12: 3 | E12: 5 | F12: A dimensão D11 da métrica DGABr analisa se a informação disponibilizada possui respaldo na legislação e nos instrumentos normativos que regulam sua publicação. No caso dos dados referentes aos "Chamados de suporte", trata-se de informação prevista na legislação brasileira, em especial nos artigos 7º e 8º da Lei de Acesso à Informação, que determinam a divulgação ativa desse tipo de dado. Dessa forma, o conjunto atende plenamente ao requisito estabelecido, alcançando o nível 5 na dimensão. | G12: =E12*D12 -> 15
A13: Legal | B13: D12 | C13: Gestão de dados sensíveis | D13: 3 | E13: 4 | F13: A análise do conjunto de dados indica a ausência de informações de natureza sensível ou pessoal. Conforme a especificação da dimensão D12 da métrica DGABr, a não aplicabilidade do tratamento de dados sensíveis a um conjunto de dados implica a atribuição do nível 4, uma vez que não há requisitos de dessensibilização ou gestão de sigilo a serem cumpridos. A avaliação, portanto, baseia-se na constatação de que o objeto avaliado não contém elementos que demandem tratamento específico de sensibilidade porém, registra-se a ausência de documentação explícita que detalhe a política de segurança ou os critérios utilizados pela instituição para classificar a sensibilidade dos dados, embora tal lacuna não impacte a pontuação desta dimensão no caso em análise. | G13: =E13*D13 -> 12
... A29: Reúso | B29: D28 | C29: Informações sobre o reúso de DGA | D29: 3 | E29: 0 | F29: A verificação no Portal Brasileiro de Dados Abertos, incluindo a consulta à funcionalidade de registro de reúso, não identificou a existência de produtos, serviços ou aplicações que utilizem o conjunto de dados analisado. A ausência de instâncias de reúso, critério avaliado na dimensão D25, impede, por conseguinte, a análise do requisito da dimensão D28, que consiste em verificar se os produtos gerados informam sobre as fontes de DGA utilizadas e sua frequência de atualização. Diante da inexistência do objeto de avaliação, atribui-se o Nível 0 a esta dimensão. A justificativa se fundamenta na definição da métrica DGABr, que classifica como inexistente a condição na qual o item avaliado não se aplica ou não é publicado. | G29: =E29*D29 -> 0
A30: Total de Pontos | G30: =SUM(G2:G29) -> 137
A31: Indicador de reúso | G31: =IF(G30<54,1,IF(G30<108,2,IF(G30<162,3,IF(G30<216,4,5)))) -> 3
A32: URL Portal próprio | D32: https://dadosabertos.ifmg.edu.br/dataset/chamados-de-suporte
A33: URL Portal Brasileiro de Dados Abertos | D33: https://dados.gov.br/dados/conjuntos-dados/chamados-de-suporte
A34: URL API | D34: https://dadosabertos.ifmg.edu.br/api/action/package_show?id=chamados-de-suporte

Sheet matriculas-iniciais-nos-cursos-
A1: Perspectiva | B1: ID | C1: Dimensão | D1: Peso | E1: Nível (0-5) | F1: Itens Observados | G1: Total
A2: Dados Abertos | B2: D1 | C2: Dados completos | D2: 1 | E2: 0 | F2: Observa-se que o conjunto de dados "Matrículas Iniciais nos Cursos Técnicos e de Graduação" não consta no PDA mais recente da instituição. De acordo com a metodologia da métrica DGABr, o PDA funciona como o instrumento de planejamento que define o escopo e os critérios de completude para um determinado conjunto de dados, incluindo a série histórica e as variáveis esperadas. A ausência de tal especificação no plano inviabiliza uma avaliação objetiva sobre se os dados publicados estão completos, conforme preconiza a dimensão D1. Diante da lacuna de evidência documental que defina o que constitui a completude para este conjunto de dados específico, atribui-se o Nível 0 – Inexistente. A justificativa para esta classificação reside no fato de que, na ausência de um compromisso formalizado no PDA, considera-se que "não há definição para o item avaliado", alinhando-se estritamente à descrição do Nível 0 na estrutura da métrica. | G2: =E2*D2 -> 0
A3: Dados Abertos | B3: D2 | C3: Dados primários | D3: 1 | E3: 0 | F3: A análise do conjunto de dados indica que sua geração é atribuída à Coordenadoria de Registro Acadêmico, unidade institucionalmente responsável pelas informações. Contudo, a evidência aponta que os dados disponibilizados foram submetidos a um processo de agregação, o que contraria o critério da dimensão D2. Conforme a métrica DGABr, dados primários são definidos por sua máxima granularidade, sendo coletados na fonte e publicados sem modificações ou agregações. Diante da constatação de que o conjunto de dados não se encontra em seu estado bruto, atribui-se o Nível 0 a esta dimensão. A justificativa para esta classificação reside no não cumprimento do requisito fundamental de primariedade, conforme estabelecido pelo modelo de avaliação. | G3: =E3*D3 -> 0
A4: Dados Abertos | B4: D3 | C4: Dados atualizados / DGA atualizado | D4: 1 | E4: 0 | F4: A análise do conjunto de dados "Matrículas Iniciais nos Cursos Técnicos e de Graduação" evidencia que este não consta no PDA mais recente da instituição. A dimensão D3 da métrica DGABr avalia o cumprimento da frequência de atualização definida para um conjunto de dados. A ausência do referido conjunto no PDA implica a inexistência de uma frequência de atualização formalmente estabelecida e publicizada, tornando inviável a verificação do cumprimento temporal. Com base nesta evidência, atribui-se o Nível 0 à dimensão. A justificativa para esta classificação reside no fato de que, para o conjunto de dados em questão, "não há definição para o item avaliado", critério que, segundo a documentação da métrica, caracteriza o Nível 0. A publicação de um conjunto de dados não previsto no PDA representa uma lacuna no planejamento gerencial que impede a avaliação objetiva de sua temporalidade. | G4: =E4*D4 -> 0
A5: Dados Abertos | B5: D4 | C5: Dados acessíveis | D5: 1 | E5: 5 | F5: A análise do conjunto de dados evidencia que o acesso é público e realizado via web, sem a requisição de mecanismos de identificação, como login ou registro prévio. Adicionalmente, a disponibilização de uma API para acesso programático e download dos recursos foi confirmada, conforme verificado no endereço eletrônico fornecido. Com base nessas observações, que demonstram o cumprimento integral (100%) dos requisitos da dimensão, atribui-se o Nível 5. | G5: =E5*D5 -> 5
A6: Dados Abertos | B6: D5 | C6: Dados processados por máquina | D6: 1 | E6: 5 | F6: Constata-se que o conjunto de dados é disponibilizado em formatos estruturados, notadamente CSV e JSON, acessíveis tanto para download direto quanto por meio de uma API. Esta constatação atende integralmente aos critérios da dimensão D5, conforme a especificação da DGABr 2.0, que para os níveis superiores (3 a 5) exige não apenas a estruturação dos dados, mas também a conformidade com especificações técnicas do ePING. Uma vez que 100% dos recursos de dados observados estão em formatos que permitem o processamento automatizado e são recomendados pelos padrões de interoperabilidade governamentais, atribui-se o Nível 5. | G6: =E6*D6 -> 5
A7: Dados Abertos | B7: D6 | C7: Acesso não discriminatório | D7: 1 | E7: 5 | F7: A análise do conjunto de dados, tanto por meio de sua página web quanto via API, evidencia que o acesso aos recursos é público e irrestrito. Não foi identificada a necessidade de cadastro, login ou qualquer outra forma de identificação para o download dos arquivos, o que atende integralmente aos critérios da dimensão D6 (Acesso não discriminatório), conforme definido pela métrica DGABr. Desta forma, atribui-se o Nível 5, uma vez que a totalidade dos pontos de acesso verificados cumpre as exigências da métrica para a pontuação máxima. | G7: =E7*D7 -> 5
A8: Dados Abertos | B8: D7 | C8: Dados não proprietários | D8: 1 | E8: 5 | F8: Constata-se, a partir da inspeção dos recursos informados, que o conjunto de dados é disponibilizado nos formatos CSV e JSON. Ambos são classificados como não-proprietários, conforme as diretrizes da perspectiva técnica da métrica DGABr. Visto que a totalidade dos dados é ofertada em formatos que cumprem integralmente o requisito da dimensão D7, a aderência é de 100%. Dessa forma, a evidência fundamenta a atribuição do Nível 5. A avaliação reflete o cumprimento integral dos padrões definidos para esta dimensão, que exige a utilização de formatos abertos para garantir o acesso e o reúso sem barreiras tecnológicas ou de licenciamento de software. | G8: =E8*D8 -> 5
A9: Dados Abertos | B9: D8 | C9: Dados livres de licença | D9: 1 | E9: 2 | F9: Observa-se que o conjunto de dados utiliza a designação "Outro (Aberta)" no campo de licença. Esta classificação é genérica e não corresponde a um modelo de licenciamento padronizado e reconhecido para dados abertos, como as licenças Creative Commons (CC) ou a Open Data Commons Open Database License (ODbL), que são referenciadas pela métrica. A ausência de um instrumento legal específico impede a definição inequívoca dos termos de uso, modificação e redistribuição, não assegurando a conformidade com os princípios de licenciamento que garantem o reúso com restrições mínimas ou nulas. Diante da evidência, atribui-se o Nível 2 a esta dimensão. A justificativa fundamenta-se no critério da métrica DGABr, segundo o qual este nível se aplica quando uma recomendação existe, neste caso, o uso de licenças abertas padrão, mas a publicação dos dados não segue o que foi definido. A utilização de uma licença não especificada, ainda que nomeada como "aberta", representa uma falha na execução da prática recomendada, comprometendo a segurança jurídica necessária para o reúso efetivo dos dados. | G9: =E9*D9 -> 2
A10: Dados Abertos | B10: D9 | C10: URIs desenhadas | D10: 1 | E10: 2 | F10: A análise das URLs dos recursos associados ao conjunto de dados evidencia a adoção de uma estrutura de nomenclatura padronizada. Existe o uso de identificadores únicos (UUIDs) para o conjunto de dados e para o recurso específico, o que contribui para a estabilidade e persistência do endereço eletrônico. Contudo, a estrutura não é considerada "amigável" ou de fácil memorização, conforme preconizado pela métrica, pois é composta por códigos alfanuméricos extensos. A identificação semântica do conteúdo depende exclusivamente do nome do arquivo ao final da URL, e não de um padrão hierárquico legível em seu caminho. Para a atribuição de um nível em conformidade com a DGABr 2.0, contudo, exige-se, para os níveis 3, 4 e 5, a comprovação de uma "política de gestão e preservação de documentos arquivísticos digitais". Adicionalmente, a análise não registra a verificação da estabilidade e persistência dos links, um componente implícito na avaliação original. Sem a evidência documental da política de preservação e um teste de estabilidade, a atribuição de um nível superior a 2 não pode ser tecnicamente fundamentada. Por isso se atribui o Nível 2. Exemplo de URL do conjunto de dados: "http://dadosabertos.ifmg.edu.br/dataset/6ec026d6-ef69-42c1-9cb2-d6c4a6f70ea6/resource/0bfa4744-26bc-4181-b75e-6cd7de0d8b84/download/conjunto-de-dados-matriculas-iniciais-nos-cursos-tecnicos-e-de-graduacao.csv". | G10: =E10*D10 -> 2
A11: Dados Abertos | B11: D10 | C11: Dados ligados | D11: 1 | E11: 0 | F11: A análise do conjunto de dados indica a ausência de vínculos com fontes de dados externas que permitam a contextualização das informações, conforme preconizado pelo princípio de dados ligados (linked data). Não foram identificadas referências, como o uso de RDF (Resource Description Framework) ou outras tecnologias semânticas, que conectem os registros a outros vocabulários ou conjuntos de dados. De acordo com a estrutura da métrica DGABr, a não implementação do item avaliado na dimensão D10 justifica a atribuição do Nível 0. | G11: =E11*D11 -> 0
A12: Legal | B12: D11 | C12: Tipo de informação | D12: 3 | E12: 5 | F12: A dimensão D11 da métrica DGABr analisa se a informação disponibilizada possui respaldo na legislação e nos instrumentos normativos que regulam sua publicação. No caso dos dados referentes aos "Matrículas Iniciais nos Cursos Técnicos e de Graduação", trata-se de informação prevista na legislação brasileira, em especial nos artigos 7º e 8º da Lei de Acesso à Informação, que determinam a divulgação ativa desse tipo de dado. Dessa forma, o conjunto atende plenamente ao requisito estabelecido, alcançando o nível 5 na dimensão. | G12: =E12*D12 -> 15
A13: Legal | B13: D12 | C13: Gestão de dados sensíveis | D13: 3 | E13: 4 | F13: A análise do conjunto de dados indica a ausência de informações de natureza sensível ou pessoal. Conforme a especificação da dimensão D12 da métrica DGABr, a não aplicabilidade do tratamento de dados sensíveis a um conjunto de dados implica a atribuição do nível 4, uma vez que não há requisitos de dessensibilização ou gestão de sigilo a serem cumpridos. A avaliação, portanto, baseia-se na constatação de que o objeto avaliado não contém elementos que demandem tratamento específico de sensibilidade porém, registra-se a ausência de documentação explícita que detalhe a política de segurança ou os critérios utilizados pela instituição para classificar a sensibilidade dos dados, embora tal lacuna não impacte a pontuação desta dimensão no caso em análise. | G13: =E13*D13 -> 12
... A29: Reúso | B29: D28 | C29: Informações sobre o reúso de DGA | D29: 3 | E29: 0 | F29: A verificação não identificou produtos, serviços ou aplicações que reutilizem o conjunto de dados analisado. A dimensão D28, "Informações sobre o reúso", avalia se os produtos gerados a partir dos DGA informam aos usuários as fontes de dados utilizadas e sua respectiva frequência de atualização. Visto que não foram localizados exemplos de reúso, torna-se inviável a verificação do cumprimento deste critério. Em conformidade com a estrutura da métrica DGABr, que estabelece o Nível 0 para situações em que o item avaliado não existe ou não se aplica, atribui-se este nível à dimensão. A ausência de aplicações que utilizem os dados é a evidência primária que fundamenta esta avaliação. | G29: =E29*D29 -> 0
A30: Total de Pontos | G30: =SUM(G2:G29) -> 130
A31: Indicador de reúso | G31: =IF(G30<54,1,IF(G30<108,2,IF(G30<162,3,IF(G30<216,4,5)))) -> 3
A32: URL Portal próprio | D32: https://dadosabertos.ifmg.edu.br/dataset/matriculas-iniciais-nos-cursos-tecnicos-e-de-graduacao
A33: URL Portal Brasileiro de Dados Abertos | D33: https://dados.gov.br/dados/conjuntos-dados/matriculas-iniciais-nos-cursos-tecnicos-e-de-graduacao
A34: URL API | D34: https://dadosabertos.ifmg.edu.br/api/action/package_show?id=matriculas-iniciais-nos-cursos-tecnicos-e-de-graduacao

Sheet quantitativo-de-discentes-e-doc
A1: Perspectiva | B1: ID | C1: Dimensão | D1: Peso | E1: Nível (0-5) | F1: Itens Observados | G1: Total
A2: Dados Abertos | B2: D1 | C2: Dados completos | D2: 1 | E2: 0 | F2: A análise do conjunto de dados "Quantitativo de Discentes e Docentes por Campus" evidencia que este não consta no PDA da instituição. O PDA é o instrumento que estabelece os parâmetros de escopo e completude para os conjuntos de dados priorizados. A ausência de previsão deste conjunto no referido plano implica a inexistência de um critério formal para aferir se os dados publicados, referentes ao ano de 2024, representam a totalidade dos registros ou um subconjunto parcial. Diante da lacuna de evidência documental que defina o que constitui um dado completo para este conjunto específico, a avaliação de sua completude torna-se metodologicamente inviável. Consequentemente, atribui-se o Nível 0 a esta dimensão, em conformidade com a definição da métrica DGABr para situações em que não há uma especificação formal para o item avaliado. | G2: =E2*D2 -> 0
A3: Dados Abertos | B3: D2 | C3: Dados primários | D3: 1 | E3: 0 | F3: Constata-se que os dados são provenientes da Coordenadoria de Registro Acadêmico, unidade institucionalmente responsável pela sua geração. No entanto, a análise do conjunto de dados revela que as informações são disponibilizadas em formato agregado, não correspondendo à sua forma primária ou de máxima granularidade. A métrica DGABr, na dimensão D2, define dados primários como aqueles coletados na fonte, sem modificações ou agregações. A disponibilização de dados exclusivamente em formato agregado impede o cumprimento dos critérios estabelecidos para os níveis superiores da dimensão. Consequentemente, a ausência de dados brutos fundamenta a atribuição do Nível 0, em conformidade com a definição da métrica para conjuntos de dados que não apresentam a característica avaliada. | G3: =E3*D3 -> 0
A4: Dados Abertos | B4: D3 | C4: Dados atualizados / DGA atualizado | D4: 1 | E4: 0 | F4: O conjunto de dados "Quantitativo de Discentes e Docentes por Campus" não consta no PDA. A ausência de menção no referido plano impede a verificação da frequência de atualização definida, critério central para a avaliação da dimensão D3. Conforme a metodologia da DGABr, a inexistência de uma periodicidade formalmente estabelecida para o conjunto de dados avaliado justifica a atribuição do Nível 0, uma vez que não há um parâmetro institucional contra o qual a temporalidade da publicação possa ser aferida. | G4: =E4*D4 -> 0
A5: Dados Abertos | B5: D4 | C5: Dados acessíveis | D5: 1 | E5: 5 | F5: Constata-se que o conjunto de dados é acessível publicamente via web, sem requerer mecanismos de login ou registro. A disponibilização de uma API para acesso programático foi igualmente verificada, conforme evidenciado pelo teste de consulta ao endereço eletrônico documentado. O cenário observado cumpre integralmente os critérios da dimensão D4 (Dados acessíveis). Desta forma, atribui-se o Nível 5, que, segundo a métrica DGABr, corresponde ao cumprimento de 100% dos requisitos para a dimensão, caracterizando a ausência de barreiras de identificação para o acesso aos dados. | G5: =E5*D5 -> 5
A6: Dados Abertos | B6: D5 | C6: Dados processados por máquina | D6: 1 | E6: 5 | F6: Verificou-se que o conjunto de dados é disponibilizado nos formatos estruturados JSON e CSV, o que garante seu processamento por máquina. Adicionalmente, a análise indicou que a estruturação dos dados está em conformidade com as especificações técnicas do ePING. Com base nessas evidências, atribui-se o Nível 5 à dimensão. A justificativa fundamenta-se no cumprimento integral (100%) dos critérios estabelecidos pela métrica DGABr 2.0 para a dimensão D5. A versão atualizada da métrica exige, para os níveis superiores de avaliação, não apenas a disponibilização em formato estruturado, mas também a aderência a padrões de interoperabilidade, requisito que foi integralmente atendido. | G6: =E6*D6 -> 5
A7: Dados Abertos | B7: D6 | C7: Acesso não discriminatório | D7: 1 | E7: 5 | F7: Verificou-se que o conjunto de dados é disponibilizado por meio de acesso público e irrestrito, tanto em sua página web quanto via API. A ausência de barreiras, como a necessidade de cadastro ou login para o download dos dados, foi confirmada por meio de testes de acesso direto aos recursos informados. Esta conformidade integral com o critério da dimensão D6 (Acesso não discriminatório) fundamenta a atribuição do Nível 5, que, segundo a métrica DGABr, corresponde ao cumprimento de 100% dos padrões definidos para a dimensão. | G7: =E7*D7 -> 5
A8: Dados Abertos | B8: D7 | C8: Dados não proprietários | D8: 1 | E8: 5 | F8: A análise do conjunto de dados e da respectiva API evidencia que os recursos são disponibilizados nos formatos CSV e JSON. Ambos os formatos são classificados como não proprietários e estão em conformidade com as recomendações técnicas da métrica DGABr e dos padrões de interoperabilidade governamental. Visto que a totalidade dos formatos ofertados atende ao critério da dimensão, que avalia o uso de padrões abertos, atribui-se o Nível 5. Esta pontuação é justificada pelo cumprimento integral (100%) do requisito, conforme estabelecido pela metodologia de avaliação da métrica. | G8: =E8*D8 -> 5
A9: Dados Abertos | B9: D8 | C9: Dados livres de licença | D9: 1 | E9: 2 | F9: Observa-se que o conjunto de dados utiliza a designação "Outro (Aberta)" no campo de licença. Esta classificação é genérica e não corresponde a um modelo de licenciamento padronizado e reconhecido para dados abertos, como as licenças Creative Commons (CC) ou a Open Data Commons Open Database License (ODbL), que são referenciadas pela métrica. A ausência de um instrumento legal específico impede a definição inequívoca dos termos de uso, modificação e redistribuição, não assegurando a conformidade com os princípios de licenciamento que garantem o reúso com restrições mínimas ou nulas. Diante da evidência, atribui-se o Nível 2 a esta dimensão. A justificativa fundamenta-se no critério da métrica DGABr, segundo o qual este nível se aplica quando uma recomendação existe, neste caso, o uso de licenças abertas padrão, mas a publicação dos dados não segue o que foi definido. A utilização de uma licença não especificada, ainda que nomeada como "aberta", representa uma falha na execução da prática recomendada, comprometendo a segurança jurídica necessária para o reúso efetivo dos dados. | G9: =E9*D9 -> 2
A10: Dados Abertos | B10: D9 | C10: URIs desenhadas | D10: 1 | E10: 2 | F10: A análise das URLs dos recursos associados ao conjunto de dados evidencia a adoção de uma estrutura de nomenclatura padronizada. Existe o uso de identificadores únicos (UUIDs) para o conjunto de dados e para o recurso específico, o que contribui para a estabilidade e persistência do endereço eletrônico. Contudo, a estrutura não é considerada "amigável" ou de fácil memorização, conforme preconizado pela métrica, pois é composta por códigos alfanuméricos extensos. A identificação semântica do conteúdo depende exclusivamente do nome do arquivo ao final da URL, e não de um padrão hierárquico legível em seu caminho. Para a atribuição de um nível em conformidade com a DGABr 2.0, contudo, exige-se, para os níveis 3, 4 e 5, a comprovação de uma "política de gestão e preservação de documentos arquivísticos digitais". Adicionalmente, a análise não registra a verificação da estabilidade e persistência dos links, um componente implícito na avaliação original. Sem a evidência documental da política de preservação e um teste de estabilidade, a atribuição de um nível superior a 2 não pode ser tecnicamente fundamentada. Por isso se atribui o Nível 2. Exemplo de URL do conjunto de dados: "http://dadosabertos.ifmg.edu.br/dataset/9e8d092a-0d49-446f-bf28-d0da40df64ea/resource/5c0189eb-cd79-430a-b419-a17e09397a24/download/conjunto-de-dados-quantitativo-de-discentes-e-docentes-por-campus.json" | G10: =E10*D10 -> 2
A11: Dados Abertos | B11: D10 | C11: Dados ligados | D11: 1 | E11: 0 | F11: A análise do conjunto de dados indica a ausência de vínculos com fontes de dados externas que permitam a contextualização das informações, conforme preconizado pelo princípio de dados ligados (linked data). Não foram identificadas referências, como o uso de RDF (Resource Description Framework) ou outras tecnologias semânticas, que conectem os registros a outros vocabulários ou conjuntos de dados. De acordo com a estrutura da métrica DGABr, a não implementação do item avaliado na dimensão D10 justifica a atribuição do Nível 0. | G11: =E11*D11 -> 0
A12: Legal | B12: D11 | C12: Tipo de informação | D12: 3 | E12: 5 | F12: A dimensão D11 da métrica DGABr analisa se a informação disponibilizada possui respaldo na legislação e nos instrumentos normativos que regulam sua publicação. No caso dos dados referentes aos "Quantitativo de Discentes e Docentes por Campus", trata-se de informação prevista na legislação brasileira, em especial nos artigos 7º e 8º da Lei de Acesso à Informação, que determinam a divulgação ativa desse tipo de dado. Dessa forma, o conjunto atende plenamente ao requisito estabelecido, alcançando o nível 5 na dimensão. | G12: =E12*D12 -> 15
A13: Legal | B13: D12 | C13: Gestão de dados sensíveis | D13: 3 | E13: 4 | F13: A análise do conjunto de dados indica a ausência de informações de natureza sensível ou pessoal. Conforme a especificação da dimensão D12 da métrica DGABr, a não aplicabilidade do tratamento de dados sensíveis a um conjunto de dados implica a atribuição do nível 4, uma vez que não há requisitos de dessensibilização ou gestão de sigilo a serem cumpridos. A avaliação, portanto, baseia-se na constatação de que o objeto avaliado não contém elementos que demandem tratamento específico de sensibilidade porém, registra-se a ausência de documentação explícita que detalhe a política de segurança ou os critérios utilizados pela instituição para classificar a sensibilidade dos dados, embora tal lacuna não impacte a pontuação desta dimensão no caso em análise. | G13: =E13*D13 -> 12
... A29: Reúso | B29: D28 | C29: Informações sobre o reúso de DGA | D29: 3 | E29: 0 | F29: A verificação de instâncias de reúso para o conjunto de dados analisado não identificou produtos ou serviços registrados. A ausência de aplicações que utilizem os DGA em questão inviabiliza, por consequência, a avaliação do critério da dimensão D28, que mensura se tais produtos informam adequadamente sobre as fontes de dados utilizadas. Portanto, atribui-se o Nível 0, em conformidade com a estrutura da métrica DGABr, que designa este nível para situações em que o objeto de avaliação não se manifesta. Registra-se que a URL fornecida na documentação de evidência (`.../quantitativo-de-discentes-e-docentes-por-campus`) remete a um conjunto de dados distinto do que está sob análise (PRONATEC), o que indica uma inconsistência na rastreabilidade do procedimento de verificação. Contudo, a consulta direta no Portal Brasileiro de Dados Abertos para o conjunto de dados do PRONATEC corrobora a ausência de registros de reúso, sustentando a classificação atribuída. | G29: =E29*D29 -> 0
A30: Total de Pontos | G30: =SUM(G2:G29) -> 128
